{"msg":"OK","server_time":"2026-03-25 04:59:21","status":200,"result":{"total_pages":133,"files":[{"download_url":"https://myvidplay.com/d/7g2883jomu4u","single_img":"https://thumbcdn.com/snaps/ar5xltebtni8rpd2.jpg","file_code":"7g2883jomu4u","length":"00:05:52","views":"7495","vw_fmt":"7.5K","uploaded":"2023-08-25 00:08:32","up_fmt":"25 Agu 2023","up_short":"25 Agu","title":"Janda Semakin Didepan Bokepin Video Indo Simontok Live Doods Pro","t_esc":"Janda Semakin Didepan Bokepin Video Indo Simontok Live Doods Pro"},{"download_url":"https://myvidplay.com/d/gjcmfq1l2rpi","single_img":"https://thumbcdn.com/snaps/utl3pk0zi8d61aix.jpg","file_code":"gjcmfq1l2rpi","length":"00:08:07","views":"3041","vw_fmt":"3.0K","uploaded":"2023-08-25 00:08:30","up_fmt":"25 Agu 2023","up_short":"25 Agu","title":"Detik Gencetan Crot Di Dalam Keenakan Bebasindo Live Bokepin Links Doodflix","t_esc":"Detik Gencetan Crot Di Dalam Keenakan Bebasindo Live Bokepin Links Doodflix"},{"download_url":"https://myvidplay.com/d/bninrckic2zr","single_img":"https://thumbcdn.com/snaps/wf87f9l7ic1qd31e.jpg","file_code":"bninrckic2zr","length":"00:01:46","views":"5051","vw_fmt":"5.1K","uploaded":"2023-08-25 00:08:28","up_fmt":"25 Agu 2023","up_short":"25 Agu","title":"Si Tocil Janda Pirang Kian Meresahkan Trim Popstream Bokepsatset Terabox Bochiel Ful","t_esc":"Si Tocil Janda Pirang Kian Meresahkan Trim Popstream Bokepsatset Terabox Bochiel Ful"},{"download_url":"https://myvidplay.com/d/vaw2ewmhww32","single_img":"https://thumbcdn.com/snaps/xz8rccv1f7e23mpf.jpg","file_code":"vaw2ewmhww32","length":"00:11:12","views":"3796","vw_fmt":"3.8K","uploaded":"2023-08-25 00:04:45","up_fmt":"25 Agu 2023","up_short":"25 Agu","title":"Janda Pirang Di Entod Selingkuhan Videos Toketbagus Lagi Viral Poophd Pejuang Lendir","t_esc":"Janda Pirang Di Entod Selingkuhan Videos Toketbagus Lagi Viral Poophd Pejuang Lendir"},{"download_url":"https://myvidplay.com/d/sztb3e4lqt8i","single_img":"https://thumbcdn.com/snaps/dxrr1n8koz33xp9y.jpg","file_code":"sztb3e4lqt8i","length":"00:18:24","views":"1941","vw_fmt":"1.9K","uploaded":"2023-08-25 00:04:29","up_fmt":"25 Agu 2023","up_short":"25 Agu","title":"Janda Pirang Goyang Bokong Seksi Indah Queen Kimcilonly Staklam Asupan Simintok Tobrut","t_esc":"Janda Pirang Goyang Bokong Seksi Indah Queen Kimcilonly Staklam Asupan Simintok Tobrut"},{"download_url":"https://myvidplay.com/d/ouqifazb3qrz","single_img":"https://thumbcdn.com/snaps/flazdi7jbcei61ka.jpg","file_code":"ouqifazb3qrz","length":"00:05:01","views":"14364","vw_fmt":"14.4K","uploaded":"2023-08-25 00:04:25","up_fmt":"25 Agu 2023","up_short":"25 Agu","title":"Janda Pirang Ajak Ponakan Ngewe Di Rumah Kosong Dood Stream Tele Sotwe","t_esc":"Janda Pirang Ajak Ponakan Ngewe Di Rumah Kosong Dood Stream Tele Sotwe"},{"download_url":"https://myvidplay.com/d/0c731gieox4u","single_img":"https://thumbcdn.com/snaps/q5qif02mkc00v76p.jpg","file_code":"0c731gieox4u","length":"00:09:05","views":"3875","vw_fmt":"3.9K","uploaded":"2023-08-25 00:04:18","up_fmt":"25 Agu 2023","up_short":"25 Agu","title":"Janda Pirang Dood Stream Pemersatu Bokep Video Simontok Terupdate Tele","t_esc":"Janda Pirang Dood Stream Pemersatu Bokep Video Simontok Terupdate Tele"},{"download_url":"https://myvidplay.com/d/a5wjwio5j40o","single_img":"https://thumbcdn.com/snaps/vkcrtv1zy61jzypu.jpg","file_code":"a5wjwio5j40o","length":"00:05:16","views":"1992","vw_fmt":"2.0K","uploaded":"2023-08-25 00:04:12","up_fmt":"25 Agu 2023","up_short":"25 Agu","title":"Ngentot Janda Pirang X Hamster Downloader Folder Lulustream Popstream Terabox","t_esc":"Ngentot Janda Pirang X Hamster Downloader Folder Lulustream Popstream Terabox"},{"download_url":"https://myvidplay.com/d/ce9h4f8xntl9","single_img":"https://thumbcdn.com/snaps/40h5r2hchegp4whh.jpg","file_code":"ce9h4f8xntl9","length":"00:07:03","views":"1587","vw_fmt":"1.6K","uploaded":"2023-08-25 00:04:05","up_fmt":"25 Agu 2023","up_short":"25 Agu","title":"Bokep Indo Disuruh Nyepong Kontol Pacar Ful Album Pemersatu Tele Bebasindo Doodsflix","t_esc":"Bokep Indo Disuruh Nyepong Kontol Pacar Ful Album Pemersatu Tele Bebasindo Doodsflix"},{"download_url":"https://myvidplay.com/d/aee9a6ko61ee","single_img":"https://thumbcdn.com/snaps/lmosnpuvs7th78kn.jpg","file_code":"aee9a6ko61ee","length":"00:06:15","views":"4983","vw_fmt":"5.0K","uploaded":"2023-08-25 00:04:00","up_fmt":"25 Agu 2023","up_short":"25 Agu","title":"Ngewe Janda Pirang Asupan Viral Memeksiana Yakwad Telegram Streaming","t_esc":"Ngewe Janda Pirang Asupan Viral Memeksiana Yakwad Telegram Streaming"},{"download_url":"https://myvidplay.com/d/q4w0yl34i6jf","single_img":"https://thumbcdn.com/snaps/1nuo5vr3x3hyacpt.jpg","file_code":"q4w0yl34i6jf","length":"00:05:23","views":"22568","vw_fmt":"22.6K","uploaded":"2023-08-25 00:03:49","up_fmt":"25 Agu 2023","up_short":"25 Agu","title":"Janda Pirang Ngulek Simontok Tiktok Telegram Live Video Viral","t_esc":"Janda Pirang Ngulek Simontok Tiktok Telegram Live Video Viral"},{"download_url":"https://myvidplay.com/d/wuirnob4lm80","single_img":"https://thumbcdn.com/snaps/d1iyogdttv132u2g.jpg","file_code":"wuirnob4lm80","length":"00:29:29","views":"1615","vw_fmt":"1.6K","uploaded":"2023-08-24 04:12:06","up_fmt":"24 Agu 2023","up_short":"24 Agu","title":"Miajoo Skandal Yang Viral Di Twitter Terupdate Doodstream Bochiel Doods Pro Videos","t_esc":"Miajoo Skandal Yang Viral Di Twitter Terupdate Doodstream Bochiel Doods Pro Videos"},{"download_url":"https://myvidplay.com/d/9xlg0lqn171n","single_img":"https://thumbcdn.com/snaps/7xquibnljzlxm65y.jpg","file_code":"9xlg0lqn171n","length":"00:06:29","views":"2612","vw_fmt":"2.6K","uploaded":"2023-08-24 04:12:06","up_fmt":"24 Agu 2023","up_short":"24 Agu","title":"Miajoo Asupan Bacol Cewek Montok Link Web Ful Album Pejuang Lendir Doodflix","t_esc":"Miajoo Asupan Bacol Cewek Montok Link Web Ful Album Pejuang Lendir Doodflix"},{"download_url":"https://myvidplay.com/d/fi2eg0lg5o7z","single_img":"https://thumbcdn.com/snaps/xih7t46r742lmrzu.jpg","file_code":"fi2eg0lg5o7z","length":"00:05:51","views":"1236","vw_fmt":"1.2K","uploaded":"2023-08-24 04:12:06","up_fmt":"24 Agu 2023","up_short":"24 Agu","title":"Miajoo Viral Dood Cantik Tobrut Dodstream Ful Album","t_esc":"Miajoo Viral Dood Cantik Tobrut Dodstream Ful Album"},{"download_url":"https://myvidplay.com/d/utqq6ql7xt1g","single_img":"https://thumbcdn.com/snaps/n25v0zelzmvy2eq8.jpg","file_code":"utqq6ql7xt1g","length":"00:15:03","views":"46190","vw_fmt":"46.2K","uploaded":"2023-08-23 16:36:25","up_fmt":"23 Agu 2023","up_short":"23 Agu","title":"Chubby Sange Omek Bokep Video Doodflix Dood Streaming Bokepsin","t_esc":"Chubby Sange Omek Bokep Video Doodflix Dood Streaming Bokepsin"},{"download_url":"https://myvidplay.com/d/ueq1bwfk5y1k","single_img":"https://thumbcdn.com/snaps/idp2lc93d69bgzhu.jpg","file_code":"ueq1bwfk5y1k","length":"00:01:37","views":"1688","vw_fmt":"1.7K","uploaded":"2023-08-23 16:20:49","up_fmt":"23 Agu 2023","up_short":"23 Agu","title":"Arizarafifa Bochiel Pemersatu Website Bokepsin Toketbagus","t_esc":"Arizarafifa Bochiel Pemersatu Website Bokepsin Toketbagus"},{"download_url":"https://myvidplay.com/d/g7zm8hi78jqx","single_img":"https://thumbcdn.com/snaps/ode3gyeuvy75ro12.jpg","file_code":"g7zm8hi78jqx","length":"00:25:53","views":"2657","vw_fmt":"2.7K","uploaded":"2023-08-23 16:20:49","up_fmt":"23 Agu 2023","up_short":"23 Agu","title":"Live Prank Ojol Bokepind Asupan Video Viral Tiktok Doodstream","t_esc":"Live Prank Ojol Bokepind Asupan Video Viral Tiktok Doodstream"},{"download_url":"https://myvidplay.com/d/lzs2ggahef4g","single_img":"https://thumbcdn.com/snaps/3m6cdxz4piohoqvg.jpg","file_code":"lzs2ggahef4g","length":"00:15:00","views":"4021","vw_fmt":"4.0K","uploaded":"2023-08-23 16:20:49","up_fmt":"23 Agu 2023","up_short":"23 Agu","title":"Pramugari Vs Tentara Pemersatu Pekoblive Popstream Dodstream Staklam","t_esc":"Pramugari Vs Tentara Pemersatu Pekoblive Popstream Dodstream Staklam"},{"download_url":"https://myvidplay.com/d/ekuq62e1e1cr","single_img":"https://thumbcdn.com/snaps/qmwy74lmxrnp9pn7.jpg","file_code":"ekuq62e1e1cr","length":"00:05:09","views":"7833","vw_fmt":"7.8K","uploaded":"2023-08-23 16:20:49","up_fmt":"23 Agu 2023","up_short":"23 Agu","title":"Bokep Viral Indo Selingkuh Dengan Mertua Hyper Sex Website Bokepin Lagi Indonesia","t_esc":"Bokep Viral Indo Selingkuh Dengan Mertua Hyper Sex Website Bokepin Lagi Indonesia"},{"download_url":"https://myvidplay.com/d/anqdgsp21bvk","single_img":"https://thumbcdn.com/snaps/rlw5eje7wxadbm1s.jpg","file_code":"anqdgsp21bvk","length":"00:04:48","views":"4175","vw_fmt":"4.2K","uploaded":"2023-08-23 16:20:49","up_fmt":"23 Agu 2023","up_short":"23 Agu","title":"Sama Kuda Dood Stream Links Tele Popstream Simontok Terabox","t_esc":"Sama Kuda Dood Stream Links Tele Popstream Simontok Terabox"},{"download_url":"https://myvidplay.com/d/zxj5tv5tlp57","single_img":"https://thumbcdn.com/snaps/0cxi34ru2d823zeb.jpg","file_code":"zxj5tv5tlp57","length":"00:06:16","views":"4706","vw_fmt":"4.7K","uploaded":"2023-08-23 16:20:49","up_fmt":"23 Agu 2023","up_short":"23 Agu","title":"Buat Mabuk Ml Di Hotel Dood Stream Bochiel Lokal Bokep Staklam Lulustream","t_esc":"Buat Mabuk Ml Di Hotel Dood Stream Bochiel Lokal Bokep Staklam Lulustream"},{"download_url":"https://myvidplay.com/d/8hx3i9h8re3b","single_img":"https://thumbcdn.com/snaps/n8zr0rv31ygir9d9.jpg","file_code":"8hx3i9h8re3b","length":"00:32:03","views":"14932","vw_fmt":"14.9K","uploaded":"2023-08-23 16:20:49","up_fmt":"23 Agu 2023","up_short":"23 Agu","title":"Adell Ngentot Dengan Adek Kelas Sekolahnya Prank Ojol Indonesia Pemersatu Bokepind Folder","t_esc":"Adell Ngentot Dengan Adek Kelas Sekolahnya Prank Ojol Indonesia Pemersatu Bokepind Folder"},{"download_url":"https://myvidplay.com/d/vq9g42poy449","single_img":"https://thumbcdn.com/snaps/ezqbwhzjihew6r8o.jpg","file_code":"vq9g42poy449","length":"00:24:43","views":"10180","vw_fmt":"10.2K","uploaded":"2023-08-23 16:20:49","up_fmt":"23 Agu 2023","up_short":"23 Agu","title":"F By Kena Jilmek Om Di Kos Prank Ojol Video Viral Tiktok","t_esc":"F By Kena Jilmek Om Di Kos Prank Ojol Video Viral Tiktok"},{"download_url":"https://myvidplay.com/d/xfsnrqaxb1pj","single_img":"https://thumbcdn.com/snaps/uu3353e55vng8im5.jpg","file_code":"xfsnrqaxb1pj","length":"00:12:01","views":"2889","vw_fmt":"2.9K","uploaded":"2023-08-23 16:20:10","up_fmt":"23 Agu 2023","up_short":"23 Agu","title":"Memek Sempit Tanpa Jembut Link Web Bokep31 Dodstream Website Doods Pro","t_esc":"Memek Sempit Tanpa Jembut Link Web Bokep31 Dodstream Website Doods Pro"},{"download_url":"https://myvidplay.com/d/bu8pw7dr01iz","single_img":"https://thumbcdn.com/snaps/794b68m20dwlav9o.jpg","file_code":"bu8pw7dr01iz","length":"00:03:05","views":"7984","vw_fmt":"8.0K","uploaded":"2023-08-23 16:20:10","up_fmt":"23 Agu 2023","up_short":"23 Agu","title":"Cewek Abg Diperkosa Dikamar Kost Ngentot Memeksiana Dood Live Tobrut","t_esc":"Cewek Abg Diperkosa Dikamar Kost Ngentot Memeksiana Dood Live Tobrut"},{"download_url":"https://myvidplay.com/d/8wyzefa9qm5r","single_img":"https://thumbcdn.com/snaps/bn7nse2wg69wsgi5.jpg","file_code":"8wyzefa9qm5r","length":"00:02:20","views":"2513","vw_fmt":"2.5K","uploaded":"2023-08-23 16:20:10","up_fmt":"23 Agu 2023","up_short":"23 Agu","title":"Nikmatnya Memek Yuli Bikin Crot Videos Bokepind Sotwe Dodstream Video Viral","t_esc":"Nikmatnya Memek Yuli Bikin Crot Videos Bokepind Sotwe Dodstream Video Viral"},{"download_url":"https://myvidplay.com/d/j4ayv8eyjn0q","single_img":"https://thumbcdn.com/snaps/qciwidgqpx6egfta.jpg","file_code":"j4ayv8eyjn0q","length":"00:02:14","views":"13642","vw_fmt":"13.6K","uploaded":"2023-08-23 16:20:06","up_fmt":"23 Agu 2023","up_short":"23 Agu","title":"Viral Selingkuh Sama Binor Live Doods Pro Pekoblive Dodstream Bokep Video","t_esc":"Viral Selingkuh Sama Binor Live Doods Pro Pekoblive Dodstream Bokep Video"},{"download_url":"https://myvidplay.com/d/heti60vdnmwu","single_img":"https://thumbcdn.com/snaps/hutq9dqbfxkn6bnt.jpg","file_code":"heti60vdnmwu","length":"00:14:31","views":"6351","vw_fmt":"6.4K","uploaded":"2023-08-23 16:20:06","up_fmt":"23 Agu 2023","up_short":"23 Agu","title":"Ayah Tiriku Entot Aku Dengan Paksa Folder Videos Links Tiktok Staklam","t_esc":"Ayah Tiriku Entot Aku Dengan Paksa Folder Videos Links Tiktok Staklam"},{"download_url":"https://myvidplay.com/d/1561m39z2hte","single_img":"https://thumbcdn.com/snaps/abscypxshru0fltm.jpg","file_code":"1561m39z2hte","length":"00:01:41","views":"4603","vw_fmt":"4.6K","uploaded":"2023-08-23 16:20:06","up_fmt":"23 Agu 2023","up_short":"23 Agu","title":"Om Kangen Ajak Tante Ke Oyo P Simontok Telegram Dodstream Full Album","t_esc":"Om Kangen Ajak Tante Ke Oyo P Simontok Telegram Dodstream Full Album"},{"download_url":"https://myvidplay.com/d/h43rdqvupdvo","single_img":"https://thumbcdn.com/snaps/73cg0pplr6wi6tjw.jpg","file_code":"h43rdqvupdvo","length":"00:15:49","views":"13646","vw_fmt":"13.6K","uploaded":"2023-08-23 16:20:01","up_fmt":"23 Agu 2023","up_short":"23 Agu","title":"Gadis Polos Bokepsin Bebasindo Viral Pekoblive Bokepind","t_esc":"Gadis Polos Bokepsin Bebasindo Viral Pekoblive Bokepind"},{"download_url":"https://myvidplay.com/d/rl5i37xm19sj","single_img":"https://thumbcdn.com/snaps/59uxq6l2mtokw0uh.jpg","file_code":"rl5i37xm19sj","length":"00:04:55","views":"5134","vw_fmt":"5.1K","uploaded":"2023-08-23 16:20:01","up_fmt":"23 Agu 2023","up_short":"23 Agu","title":"Alfil Ml Gairah Buangettt Prank Ojol Pejuang Lendir Dood Tele Lokal Doods","t_esc":"Alfil Ml Gairah Buangettt Prank Ojol Pejuang Lendir Dood Tele Lokal Doods"},{"download_url":"https://myvidplay.com/d/fi0bzt5vh9c1","single_img":"https://thumbcdn.com/snaps/0zmua5nfo3tnl060.jpg","file_code":"fi0bzt5vh9c1","length":"00:05:03","views":"16727","vw_fmt":"16.7K","uploaded":"2023-08-23 16:20:01","up_fmt":"23 Agu 2023","up_short":"23 Agu","title":"Layani Ml Ibu Kos Prank Ojol Toketbagus Videos Asupan Doodflix Pemersatu","t_esc":"Layani Ml Ibu Kos Prank Ojol Toketbagus Videos Asupan Doodflix Pemersatu"},{"download_url":"https://myvidplay.com/d/uwruu47y655e","single_img":"https://thumbcdn.com/snaps/ehkfz5f6rb0o7d5k.jpg","file_code":"uwruu47y655e","length":"00:06:29","views":"55459","vw_fmt":"55.5K","uploaded":"2023-08-23 16:19:57","up_fmt":"23 Agu 2023","up_short":"23 Agu","title":"Kakek Ngentot Tante Sampai Crot Bangey Dood Stream Bokep Video Xpanas Dodstream","t_esc":"Kakek Ngentot Tante Sampai Crot Bangey Dood Stream Bokep Video Xpanas Dodstream"},{"download_url":"https://myvidplay.com/d/ct9zmj9qjwqf","single_img":"https://thumbcdn.com/snaps/deddooq45nrhab0j.jpg","file_code":"ct9zmj9qjwqf","length":"00:09:00","views":"4108","vw_fmt":"4.1K","uploaded":"2023-08-23 16:19:57","up_fmt":"23 Agu 2023","up_short":"23 Agu","title":"Di Booking Mahasiswa Crot Cepet Dood Memeksiana Ful Album Lulustream Videos","t_esc":"Di Booking Mahasiswa Crot Cepet Dood Memeksiana Ful Album Lulustream Videos"},{"download_url":"https://myvidplay.com/d/02z2jk9cv2u6","single_img":"https://thumbcdn.com/snaps/oea7bc9c7b6zd8fl.jpg","file_code":"02z2jk9cv2u6","length":"00:11:17","views":"16737","vw_fmt":"16.7K","uploaded":"2023-08-23 16:19:57","up_fmt":"23 Agu 2023","up_short":"23 Agu","title":"Crot Di Atas Perut Adek Tiri Iedp Xpanas Links Bokep Dood Streaming","t_esc":"Crot Di Atas Perut Adek Tiri Iedp Xpanas Links Bokep Dood Streaming"},{"download_url":"https://myvidplay.com/d/ved3pnop94mw","single_img":"https://thumbcdn.com/snaps/1gtjkl0kvi37o3qk.jpg","file_code":"ved3pnop94mw","length":"00:02:22","views":"15674","vw_fmt":"15.7K","uploaded":"2023-08-23 16:19:57","up_fmt":"23 Agu 2023","up_short":"23 Agu","title":"Siskaeee Prank Petani Poophd Lokal Links Viral Tele","t_esc":"Siskaeee Prank Petani Poophd Lokal Links Viral Tele"},{"download_url":"https://myvidplay.com/d/vbmh9qems14a","single_img":"https://thumbcdn.com/snaps/tkzrzodynud28hx4.jpg","file_code":"vbmh9qems14a","length":"00:13:26","views":"11678","vw_fmt":"11.7K","uploaded":"2023-08-23 16:19:46","up_fmt":"23 Agu 2023","up_short":"23 Agu","title":"X Bokep Indo Viral Devina Vcs Full Video Devshaaa Toketbagus Telegram Bebasindo","t_esc":"X Bokep Indo Viral Devina Vcs Full Video Devshaaa Toketbagus Telegram Bebasindo"},{"download_url":"https://myvidplay.com/d/bxmik1oxxywg","single_img":"https://thumbcdn.com/snaps/moqbcbih3wnncben.jpg","file_code":"bxmik1oxxywg","length":"00:01:35","views":"3411","vw_fmt":"3.4K","uploaded":"2023-08-23 16:19:46","up_fmt":"23 Agu 2023","up_short":"23 Agu","title":"Jilbab Imzizra Video Lainnya Cek Tele Bungajanda Dood Stream Original Bokepind Dodstream","t_esc":"Jilbab Imzizra Video Lainnya Cek Tele Bungajanda Dood Stream Original Bokepind Dodstream"},{"download_url":"https://myvidplay.com/d/50va36dm2bbe","single_img":"https://thumbcdn.com/snaps/o4v5kl61nd9v2uds.jpg","file_code":"50va36dm2bbe","length":"00:01:47","views":"36619","vw_fmt":"36.6K","uploaded":"2023-08-23 16:19:46","up_fmt":"23 Agu 2023","up_short":"23 Agu","title":"Bu Guru Privat Viral Jilbab Simintok Videos Bokepsatset Full Album","t_esc":"Bu Guru Privat Viral Jilbab Simintok Videos Bokepsatset Full Album"},{"download_url":"https://myvidplay.com/d/sk5vqebwdrmf","single_img":"https://thumbcdn.com/snaps/1z6p114m411rkdwg.jpg","file_code":"sk5vqebwdrmf","length":"00:13:56","views":"6074","vw_fmt":"6.1K","uploaded":"2023-08-23 16:19:46","up_fmt":"23 Agu 2023","up_short":"23 Agu","title":"Ngajak Pacaran Di Kebun Links Doods Pro Jilbab Lagi Viral Tele","t_esc":"Ngajak Pacaran Di Kebun Links Doods Pro Jilbab Lagi Viral Tele"},{"download_url":"https://myvidplay.com/d/2jnmi4w4c3va","single_img":"https://thumbcdn.com/snaps/ai9xzufa9uc73e6o.jpg","file_code":"2jnmi4w4c3va","length":"00:02:17","views":"16760","vw_fmt":"16.8K","uploaded":"2023-08-23 16:19:46","up_fmt":"23 Agu 2023","up_short":"23 Agu","title":"Bokep Indo Kakak Beradik Ngentot Dirumah Sepi Bokepind Tobrut Dood Asupan Folder","t_esc":"Bokep Indo Kakak Beradik Ngentot Dirumah Sepi Bokepind Tobrut Dood Asupan Folder"},{"download_url":"https://myvidplay.com/d/4n4m2jemgs3r","single_img":"https://thumbcdn.com/snaps/uawlsfd3eg8lcsmx.jpg","file_code":"4n4m2jemgs3r","length":"00:07:00","views":"2637","vw_fmt":"2.6K","uploaded":"2023-08-23 16:19:39","up_fmt":"23 Agu 2023","up_short":"23 Agu","title":"Sejoli Live Bercocok Tanam Fb Wota Ngesimp V Doods Pro Memeksiana Bokepsatset","t_esc":"Sejoli Live Bercocok Tanam Fb Wota Ngesimp V Doods Pro Memeksiana Bokepsatset"},{"download_url":"https://myvidplay.com/d/uodd2bfqneif","single_img":"https://thumbcdn.com/snaps/aox1ywz437p2cq9n.jpg","file_code":"uodd2bfqneif","length":"00:01:50","views":"4013","vw_fmt":"4.0K","uploaded":"2023-08-23 16:19:39","up_fmt":"23 Agu 2023","up_short":"23 Agu","title":"Bokep Indo Viral Suster Dengan Pasien Dari Jogja Bokepind Habis Mandi Mas","t_esc":"Bokep Indo Viral Suster Dengan Pasien Dari Jogja Bokepind Habis Mandi Mas"},{"download_url":"https://myvidplay.com/d/yzicanvbwvel","single_img":"https://thumbcdn.com/snaps/bmjyknumbixxpztz.jpg","file_code":"yzicanvbwvel","length":"00:02:20","views":"215740","vw_fmt":"215.7K","uploaded":"2023-08-23 11:38:56","up_fmt":"23 Agu 2023","up_short":"23 Agu","title":"Tante Girang Ngewe Sama Hyper Banget Ful Album Bokepsin Video Bokep Bebasindo","t_esc":"Tante Girang Ngewe Sama Hyper Banget Ful Album Bokepsin Video Bokep Bebasindo"},{"download_url":"https://myvidplay.com/d/vm2hdziwbhew","single_img":"https://thumbcdn.com/snaps/3imqcqhsa914f69d.jpg","file_code":"vm2hdziwbhew","length":"00:07:51","views":"920","vw_fmt":"920","uploaded":"2023-08-22 11:16:35","up_fmt":"22 Agu 2023","up_short":"22 Agu","title":"Tante Toket Gede Montok Ml Apj Dood Tele Bokep Video Terupdate Telegram","t_esc":"Tante Toket Gede Montok Ml Apj Dood Tele Bokep Video Terupdate Telegram"},{"download_url":"https://myvidplay.com/d/a9y5adjn620c","single_img":"https://thumbcdn.com/snaps/vnvg258t4i2wxwev.jpg","file_code":"a9y5adjn620c","length":"00:10:00","views":"815","vw_fmt":"815","uploaded":"2023-08-22 11:16:34","up_fmt":"22 Agu 2023","up_short":"22 Agu","title":"Tante Montok Ngentot Bdmv Bokep Video Folder Sma Staklam Live","t_esc":"Tante Montok Ngentot Bdmv Bokep Video Folder Sma Staklam Live"},{"download_url":"https://myvidplay.com/d/yg0xe53bdqzj","single_img":"https://thumbcdn.com/snaps/d9i9f04wy8idpq2m.jpg","file_code":"yg0xe53bdqzj","length":"00:02:43","views":"1561","vw_fmt":"1.6K","uploaded":"2023-08-22 11:16:32","up_fmt":"22 Agu 2023","up_short":"22 Agu","title":"Bacol Vcs Cewek Semok Toket Montok Bugil Bokep Video Memeksiana Viral Bokepin","t_esc":"Bacol Vcs Cewek Semok Toket Montok Bugil Bokep Video Memeksiana Viral Bokepin"},{"download_url":"https://myvidplay.com/d/9cvem1ygo3v2","single_img":"https://thumbcdn.com/snaps/5vwcykfzuylrss4d.jpg","file_code":"9cvem1ygo3v2","length":"00:07:10","views":"948","vw_fmt":"948","uploaded":"2023-08-22 11:16:30","up_fmt":"22 Agu 2023","up_short":"22 Agu","title":"Pasutri Malming Link Web Bokepin Terabox Video Indo Cantik Tobrut","t_esc":"Pasutri Malming Link Web Bokepin Terabox Video Indo Cantik Tobrut"},{"download_url":"https://myvidplay.com/d/jxurhxtgfr0w","single_img":"https://thumbcdn.com/snaps/n259iaddnwrxpead.jpg","file_code":"jxurhxtgfr0w","length":"00:30:55","views":"535","vw_fmt":"535","uploaded":"2023-08-22 11:16:28","up_fmt":"22 Agu 2023","up_short":"22 Agu","title":"Ew Tante Semok Emang Enak Update Ful Album Video Indo Bokep Dood","t_esc":"Ew Tante Semok Emang Enak Update Ful Album Video Indo Bokep Dood"},{"download_url":"https://myvidplay.com/d/qbzfkua3u7m0","single_img":"https://thumbcdn.com/snaps/qb99nra7skbr3z66.jpg","file_code":"qbzfkua3u7m0","length":"00:10:57","views":"14067","vw_fmt":"14.1K","uploaded":"2023-08-22 11:16:27","up_fmt":"22 Agu 2023","up_short":"22 Agu","title":"Keindahan Bigo Hot Pascol Live Indonesia Terbaru Joget Goyang Tante Toge Semok","t_esc":"Keindahan Bigo Hot Pascol Live Indonesia Terbaru Joget Goyang Tante Toge Semok"},{"download_url":"https://myvidplay.com/d/tncwd82kyg84","single_img":"https://thumbcdn.com/snaps/i5yw54q8jmlqahj4.jpg","file_code":"tncwd82kyg84","length":"00:01:41","views":"2487","vw_fmt":"2.5K","uploaded":"2023-08-22 11:16:25","up_fmt":"22 Agu 2023","up_short":"22 Agu","title":"Body Nya Semok Banget Pejuang Lendir Doodflix Bochiel Live Bokepsin","t_esc":"Body Nya Semok Banget Pejuang Lendir Doodflix Bochiel Live Bokepsin"},{"download_url":"https://myvidplay.com/d/9ajc03iedojz","single_img":"https://thumbcdn.com/snaps/gsjwlorh3sq30m9p.jpg","file_code":"9ajc03iedojz","length":"00:17:14","views":"6250","vw_fmt":"6.2K","uploaded":"2023-08-22 11:16:24","up_fmt":"22 Agu 2023","up_short":"22 Agu","title":"Goyangan Tante Enak Banget I Videos Viral Jilbab Telegram Xpanas","t_esc":"Goyangan Tante Enak Banget I Videos Viral Jilbab Telegram Xpanas"},{"download_url":"https://myvidplay.com/d/pg69s8px79g4","single_img":"https://thumbcdn.com/snaps/62gcsizyajdm8vii.jpg","file_code":"pg69s8px79g4","length":"00:12:59","views":"15291","vw_fmt":"15.3K","uploaded":"2023-08-22 11:16:23","up_fmt":"22 Agu 2023","up_short":"22 Agu","title":"Malemjumat Bokep Barat Dimanjain Cewek Toket Brutal Tobrut Indo Cilbo Bokepsin Pekoblive","t_esc":"Malemjumat Bokep Barat Dimanjain Cewek Toket Brutal Tobrut Indo Cilbo Bokepsin Pekoblive"},{"download_url":"https://myvidplay.com/d/vvl757uu2fjn","single_img":"https://thumbcdn.com/snaps/44qbdrzmfcm5eyjl.jpg","file_code":"vvl757uu2fjn","length":"00:09:12","views":"6732","vw_fmt":"6.7K","uploaded":"2023-08-22 11:16:22","up_fmt":"22 Agu 2023","up_short":"22 Agu","title":"Stw Bbw Crott Dimekii Dood Stream Bokepsin Viral Bokepsatset Live Terabox","t_esc":"Stw Bbw Crott Dimekii Dood Stream Bokepsin Viral Bokepsatset Live Terabox"},{"download_url":"https://myvidplay.com/d/sk40sjtp0102","single_img":"https://thumbcdn.com/snaps/tft0v8giqzp2ofi1.jpg","file_code":"sk40sjtp0102","length":"00:18:28","views":"10143","vw_fmt":"10.1K","uploaded":"2023-08-22 11:16:21","up_fmt":"22 Agu 2023","up_short":"22 Agu","title":"Ibu Lurah Ngentot Dengan Dildo Dan Kontol Suami Orang Sampai Squirts Reu","t_esc":"Ibu Lurah Ngentot Dengan Dildo Dan Kontol Suami Orang Sampai Squirts Reu"},{"download_url":"https://myvidplay.com/d/s3htlxp3wq8l","single_img":"https://thumbcdn.com/snaps/jls12c00qaxltf7b.jpg","file_code":"s3htlxp3wq8l","length":"00:07:18","views":"10241","vw_fmt":"10.2K","uploaded":"2023-08-22 11:16:19","up_fmt":"22 Agu 2023","up_short":"22 Agu","title":"Bokep Tante Montok Semok Tobrut Dientot Kontol Hitam Video Sma Ful Album","t_esc":"Bokep Tante Montok Semok Tobrut Dientot Kontol Hitam Video Sma Ful Album"},{"download_url":"https://myvidplay.com/d/h5a8tdvw4qnh","single_img":"https://thumbcdn.com/snaps/t3tgyqeri0tcw7b4.jpg","file_code":"h5a8tdvw4qnh","length":"00:02:46","views":"524","vw_fmt":"524","uploaded":"2023-08-22 11:16:18","up_fmt":"22 Agu 2023","up_short":"22 Agu","title":"Bokep Terbaru Genjot Tante Montok Semok Sangean Dodstream Live Tobrut Doodflix Dood","t_esc":"Bokep Terbaru Genjot Tante Montok Semok Sangean Dodstream Live Tobrut Doodflix Dood"},{"download_url":"https://myvidplay.com/d/0pp2rh19w1wv","single_img":"https://thumbcdn.com/snaps/0oylourqhu8phj5a.jpg","file_code":"0pp2rh19w1wv","length":"00:02:15","views":"47123","vw_fmt":"47.1K","uploaded":"2023-08-22 11:15:50","up_fmt":"22 Agu 2023","up_short":"22 Agu","title":"Bokep Indo Tante Keenakan Digenjot Mendesah Penuh Nikmat Play Dood Stream","t_esc":"Bokep Indo Tante Keenakan Digenjot Mendesah Penuh Nikmat Play Dood Stream"},{"download_url":"https://myvidplay.com/d/12ehse5e8hoc","single_img":"https://thumbcdn.com/snaps/d5lx8xmbw5tnwmqv.jpg","file_code":"12ehse5e8hoc","length":"00:13:47","views":"9846","vw_fmt":"9.8K","uploaded":"2023-08-22 11:15:48","up_fmt":"22 Agu 2023","up_short":"22 Agu","title":"Bokep Indo Prank Ojol Liadani Sange Miss Pascol Semok Montok Dood Stream","t_esc":"Bokep Indo Prank Ojol Liadani Sange Miss Pascol Semok Montok Dood Stream"},{"download_url":"https://myvidplay.com/d/yf6r1ei25o7h","single_img":"https://thumbcdn.com/snaps/83n4az2w07ept3x0.jpg","file_code":"yf6r1ei25o7h","length":"00:05:18","views":"2669","vw_fmt":"2.7K","uploaded":"2023-08-22 11:15:47","up_fmt":"22 Agu 2023","up_short":"22 Agu","title":"Semok Montok Berkumis Sarah Dinara Dood Stream Viral Bokep Tiktok","t_esc":"Semok Montok Berkumis Sarah Dinara Dood Stream Viral Bokep Tiktok"},{"download_url":"https://myvidplay.com/d/2lkdf1w7h3np","single_img":"https://thumbcdn.com/snaps/wuk5bt9hpyipijzv.jpg","file_code":"2lkdf1w7h3np","length":"00:21:46","views":"674","vw_fmt":"674","uploaded":"2023-08-22 11:15:46","up_fmt":"22 Agu 2023","up_short":"22 Agu","title":"Betty Payudara Jumbo Live Martha Jones Tante Semok Montok Bebasindo Doodflix Popstream","t_esc":"Betty Payudara Jumbo Live Martha Jones Tante Semok Montok Bebasindo Doodflix Popstream"},{"download_url":"https://myvidplay.com/d/vk4lioezj10y","single_img":"https://thumbcdn.com/snaps/qzr4nk30nouwyr46.jpg","file_code":"vk4lioezj10y","length":"00:12:10","views":"323","vw_fmt":"323","uploaded":"2023-08-22 11:15:39","up_fmt":"22 Agu 2023","up_short":"22 Agu","title":"Toket Gede Brutal Miss Betty Martha Jones Tante Semok Montok Cantik Tobrut","t_esc":"Toket Gede Brutal Miss Betty Martha Jones Tante Semok Montok Cantik Tobrut"},{"download_url":"https://myvidplay.com/d/kvb42hsr5bp6","single_img":"https://thumbcdn.com/snaps/zqafk4qo02z7h9g7.jpg","file_code":"kvb42hsr5bp6","length":"00:04:46","views":"683","vw_fmt":"683","uploaded":"2023-08-22 11:15:38","up_fmt":"22 Agu 2023","up_short":"22 Agu","title":"Toket Gede Tante Jones Martha Semok Montok Update Pemersatu Streaming Jilbab Bokepsin","t_esc":"Toket Gede Tante Jones Martha Semok Montok Update Pemersatu Streaming Jilbab Bokepsin"},{"download_url":"https://myvidplay.com/d/bab55aj48xt1","single_img":"https://thumbcdn.com/snaps/hiocoxapzpo12lnx.jpg","file_code":"bab55aj48xt1","length":"00:01:04","views":"7275","vw_fmt":"7.3K","uploaded":"2023-08-22 11:15:36","up_fmt":"22 Agu 2023","up_short":"22 Agu","title":"Tante Semokk Mekkyy Tembem Colmek Sampe Crott Bokep31 Video Bokep Bochiel Ngentot","t_esc":"Tante Semokk Mekkyy Tembem Colmek Sampe Crott Bokep31 Video Bokep Bochiel Ngentot"},{"download_url":"https://myvidplay.com/d/krk76x6hb6ty","single_img":"https://thumbcdn.com/snaps/oazb5u0b9k63uz00.jpg","file_code":"krk76x6hb6ty","length":"00:22:02","views":"1410","vw_fmt":"1.4K","uploaded":"2023-08-22 11:15:34","up_fmt":"22 Agu 2023","up_short":"22 Agu","title":"Bokep Indo Prank Tukang Paket Tante Semok Montok Ngentot Video Pekoblive Terupdate","t_esc":"Bokep Indo Prank Tukang Paket Tante Semok Montok Ngentot Video Pekoblive Terupdate"},{"download_url":"https://myvidplay.com/d/zg4sad2giu6c","single_img":"https://thumbcdn.com/snaps/p8souu4ictf704cz.jpg","file_code":"zg4sad2giu6c","length":"00:02:20","views":"1144","vw_fmt":"1.1K","uploaded":"2023-08-22 11:15:31","up_fmt":"22 Agu 2023","up_short":"22 Agu","title":"Bokep Audreyand Sadie Pasangan Lesbi Ngewe Audreyandsadie Of Barat Abg Tante Montok","t_esc":"Bokep Audreyand Sadie Pasangan Lesbi Ngewe Audreyandsadie Of Barat Abg Tante Montok"},{"download_url":"https://myvidplay.com/d/isbyz7g13hsa","single_img":"https://thumbcdn.com/snaps/dts6ox8gpd5qhr4n.jpg","file_code":"isbyz7g13hsa","length":"00:11:20","views":"3332","vw_fmt":"3.3K","uploaded":"2023-08-22 11:15:31","up_fmt":"22 Agu 2023","up_short":"22 Agu","title":"Bokep Indo Montok Tante Semok Ketagihan Dientot Doggystyle Bokepsin Com Update Live","t_esc":"Bokep Indo Montok Tante Semok Ketagihan Dientot Doggystyle Bokepsin Com Update Live"},{"download_url":"https://myvidplay.com/d/qe9bh39slkkl","single_img":"https://thumbcdn.com/snaps/nd14lgydyaeg810d.jpg","file_code":"qe9bh39slkkl","length":"00:02:00","views":"9360","vw_fmt":"9.4K","uploaded":"2023-08-22 11:15:22","up_fmt":"22 Agu 2023","up_short":"22 Agu","title":"Ngentot Tante Rosa Janda Semok Montok Anak Dua Video Colmek Doods Pro","t_esc":"Ngentot Tante Rosa Janda Semok Montok Anak Dua Video Colmek Doods Pro"},{"download_url":"https://myvidplay.com/d/bcyt87c57gcf","single_img":"https://thumbcdn.com/snaps/06xhjrafdkdcelwp.jpg","file_code":"bcyt87c57gcf","length":"00:03:22","views":"9232","vw_fmt":"9.2K","uploaded":"2023-08-22 11:15:21","up_fmt":"22 Agu 2023","up_short":"22 Agu","title":"Bokep Indo Hijab Tante Yona Jilboobsr Colmek Jahira Montok Semok","t_esc":"Bokep Indo Hijab Tante Yona Jilboobsr Colmek Jahira Montok Semok"},{"download_url":"https://myvidplay.com/d/gnpr1s6k5gnj","single_img":"https://thumbcdn.com/snaps/jq3lqkathsu035lb.jpg","file_code":"gnpr1s6k5gnj","length":"00:59:46","views":"5261","vw_fmt":"5.3K","uploaded":"2023-08-22 11:15:20","up_fmt":"22 Agu 2023","up_short":"22 Agu","title":"Bokep Indo Live Tante Cantik Montok Semok Toge Bokepin Update Full Album","t_esc":"Bokep Indo Live Tante Cantik Montok Semok Toge Bokepin Update Full Album"},{"download_url":"https://myvidplay.com/d/m40tjnzsznmh","single_img":"https://thumbcdn.com/snaps/rugmyripuvs2yiac.jpg","file_code":"m40tjnzsznmh","length":"00:09:36","views":"2447","vw_fmt":"2.4K","uploaded":"2023-08-22 11:15:19","up_fmt":"22 Agu 2023","up_short":"22 Agu","title":"Bokep Indo Tubuh Semok Montok Tante Princesss Bbwpku Video Colmek Pemersatu Dodstream","t_esc":"Bokep Indo Tubuh Semok Montok Tante Princesss Bbwpku Video Colmek Pemersatu Dodstream"},{"download_url":"https://myvidplay.com/d/i05w3lahpxto","single_img":"https://thumbcdn.com/snaps/rhjc2rjaiddq9eph.jpg","file_code":"i05w3lahpxto","length":"01:00:00","views":"2325","vw_fmt":"2.3K","uploaded":"2023-08-22 11:15:18","up_fmt":"22 Agu 2023","up_short":"22 Agu","title":"Bokep Indo Ayang Montok Ngentot Wot Live Miss Ay Tante Semok","t_esc":"Bokep Indo Ayang Montok Ngentot Wot Live Miss Ay Tante Semok"},{"download_url":"https://myvidplay.com/d/vtekeetxtfmf","single_img":"https://thumbcdn.com/snaps/si3dyunsonzrbo2m.jpg","file_code":"vtekeetxtfmf","length":"00:12:37","views":"12755","vw_fmt":"12.8K","uploaded":"2023-08-22 11:15:17","up_fmt":"22 Agu 2023","up_short":"22 Agu","title":"Bokep Ngentot Janda Montok Semok Toket Gede Brutal Ava Addams Barat Tante","t_esc":"Bokep Ngentot Janda Montok Semok Toket Gede Brutal Ava Addams Barat Tante"},{"download_url":"https://myvidplay.com/d/k1p9pqyvtz55","single_img":"https://thumbcdn.com/snaps/czvrw1g95ksa28jk.jpg","file_code":"k1p9pqyvtz55","length":"00:08:45","views":"1313","vw_fmt":"1.3K","uploaded":"2023-08-22 11:15:15","up_fmt":"22 Agu 2023","up_short":"22 Agu","title":"Semok Montok Tante Maya Mustika Dance Hot Bebasindo Bochiel Asupan Viral Pejuang","t_esc":"Semok Montok Tante Maya Mustika Dance Hot Bebasindo Bochiel Asupan Viral Pejuang"},{"download_url":"https://myvidplay.com/d/dhef1x2mwpng","single_img":"https://thumbcdn.com/snaps/bmyvt29b6pw5g8c0.jpg","file_code":"dhef1x2mwpng","length":"00:37:09","views":"4310","vw_fmt":"4.3K","uploaded":"2023-08-22 11:15:14","up_fmt":"22 Agu 2023","up_short":"22 Agu","title":"Dinara Viral Bokep Tiktok Folder Poophd Doods Pro","t_esc":"Dinara Viral Bokep Tiktok Folder Poophd Doods Pro"},{"download_url":"https://myvidplay.com/d/9jv65womuhu1","single_img":"https://thumbcdn.com/snaps/on3rjhn7uopy22q4.jpg","file_code":"9jv65womuhu1","length":"00:14:47","views":"460","vw_fmt":"460","uploaded":"2023-08-22 11:15:11","up_fmt":"22 Agu 2023","up_short":"22 Agu","title":"Bokep Indo Tante Montok Toket Brutal Pemuas Nafsu Hhh Maskkim Onlyfans Semok","t_esc":"Bokep Indo Tante Montok Toket Brutal Pemuas Nafsu Hhh Maskkim Onlyfans Semok"},{"download_url":"https://myvidplay.com/d/5o4erfxrnpys","single_img":"https://thumbcdn.com/snaps/e3iytkl03baxs0ay.jpg","file_code":"5o4erfxrnpys","length":"00:05:20","views":"2202","vw_fmt":"2.2K","uploaded":"2023-08-22 11:15:11","up_fmt":"22 Agu 2023","up_short":"22 Agu","title":"Bokep Indo Tante Montok Toge Bulat Semok Colmek Bokepsatset Sotwe Viral Bokepin","t_esc":"Bokep Indo Tante Montok Toge Bulat Semok Colmek Bokepsatset Sotwe Viral Bokepin"},{"download_url":"https://myvidplay.com/d/keks5uplioym","single_img":"https://thumbcdn.com/snaps/bruw61ywyt48ch3e.jpg","file_code":"keks5uplioym","length":"00:02:20","views":"13926","vw_fmt":"13.9K","uploaded":"2023-08-22 11:15:09","up_fmt":"22 Agu 2023","up_short":"22 Agu","title":"Bokep Audrey And Sadie Pasangan Lesbi Ngewe Audreyandsadie Of Barat Abg Tante","t_esc":"Bokep Audrey And Sadie Pasangan Lesbi Ngewe Audreyandsadie Of Barat Abg Tante"},{"download_url":"https://myvidplay.com/d/yyrgg31bwrkx","single_img":"https://thumbcdn.com/snaps/y1ys40i54atmxmtt.jpg","file_code":"yyrgg31bwrkx","length":"00:13:55","views":"1467","vw_fmt":"1.5K","uploaded":"2023-08-22 11:15:07","up_fmt":"22 Agu 2023","up_short":"22 Agu","title":"Bokep Indo Ebot Binal Zara Montok Semok Zaraaa Tante Tobrut Doodflix Tiktok","t_esc":"Bokep Indo Ebot Binal Zara Montok Semok Zaraaa Tante Tobrut Doodflix Tiktok"},{"download_url":"https://myvidplay.com/d/gp1sessctsb0","single_img":"https://thumbcdn.com/snaps/kb1rslq0897ubnrg.jpg","file_code":"gp1sessctsb0","length":"00:32:27","views":"9320","vw_fmt":"9.3K","uploaded":"2023-08-22 11:15:06","up_fmt":"22 Agu 2023","up_short":"22 Agu","title":"Bokep Indo Live Zara Binal Godain Pascol Zaraaa Montok Semok Tante Doodflix","t_esc":"Bokep Indo Live Zara Binal Godain Pascol Zaraaa Montok Semok Tante Doodflix"},{"download_url":"https://myvidplay.com/d/mhbyd3cewrou","single_img":"https://thumbcdn.com/snaps/qasa96pn1nsw9whs.jpg","file_code":"mhbyd3cewrou","length":"00:29:55","views":"1231","vw_fmt":"1.2K","uploaded":"2023-08-22 11:14:58","up_fmt":"22 Agu 2023","up_short":"22 Agu","title":"Bokep Indo Remas Toket Bulat Zara Pantat Besar Zaraaa Montok Semok Tante","t_esc":"Bokep Indo Remas Toket Bulat Zara Pantat Besar Zaraaa Montok Semok Tante"},{"download_url":"https://myvidplay.com/d/2zwdpvwzk63y","single_img":"https://thumbcdn.com/snaps/xdekt4ecmb2wtlkb.jpg","file_code":"2zwdpvwzk63y","length":"00:28:04","views":"3261","vw_fmt":"3.3K","uploaded":"2023-08-22 11:14:57","up_fmt":"22 Agu 2023","up_short":"22 Agu","title":"Bokep Indo Zara Ajak Crot Bareng Malam Minggu Zaraaa Montok Semok Tante","t_esc":"Bokep Indo Zara Ajak Crot Bareng Malam Minggu Zaraaa Montok Semok Tante"},{"download_url":"https://myvidplay.com/d/puoypf1o0z1k","single_img":"https://thumbcdn.com/snaps/xz9qntxytfysidsl.jpg","file_code":"puoypf1o0z1k","length":"00:09:45","views":"17006","vw_fmt":"17.0K","uploaded":"2023-08-22 11:14:57","up_fmt":"22 Agu 2023","up_short":"22 Agu","title":"Bokep Indo Zara Bohay Mode Barbar Telanjang Zaraaa Montok Semok Tante Staklam","t_esc":"Bokep Indo Zara Bohay Mode Barbar Telanjang Zaraaa Montok Semok Tante Staklam"},{"download_url":"https://myvidplay.com/d/p516jrrdjcfj","single_img":"https://thumbcdn.com/snaps/yefe0krx1qugtb46.jpg","file_code":"p516jrrdjcfj","length":"00:15:20","views":"18443","vw_fmt":"18.4K","uploaded":"2023-08-22 11:14:56","up_fmt":"22 Agu 2023","up_short":"22 Agu","title":"Bokep Indo Zara Binal Desah Remas Puting Susunya Zaraaa Montok Semok Tante","t_esc":"Bokep Indo Zara Binal Desah Remas Puting Susunya Zaraaa Montok Semok Tante"},{"download_url":"https://myvidplay.com/d/utf8svevc1ke","single_img":"https://thumbcdn.com/snaps/wvf6pvu8tdqs60fe.jpg","file_code":"utf8svevc1ke","length":"00:09:45","views":"14286","vw_fmt":"14.3K","uploaded":"2023-08-22 11:14:55","up_fmt":"22 Agu 2023","up_short":"22 Agu","title":"Bokep Indo Zara Bugil Lepas Kemeja Putih Rare Zaraaa Montok Semok Tante","t_esc":"Bokep Indo Zara Bugil Lepas Kemeja Putih Rare Zaraaa Montok Semok Tante"},{"download_url":"https://myvidplay.com/d/dlm528zlxp78","single_img":"https://thumbcdn.com/snaps/egjhgn3xgiaselok.jpg","file_code":"dlm528zlxp78","length":"01:08:05","views":"9599","vw_fmt":"9.6K","uploaded":"2023-08-22 11:14:55","up_fmt":"22 Agu 2023","up_short":"22 Agu","title":"Bokep Indo Momoka Alias Zara Montok Mango Zaraaa Semok Tante Viral Indonesia","t_esc":"Bokep Indo Momoka Alias Zara Montok Mango Zaraaa Semok Tante Viral Indonesia"},{"download_url":"https://myvidplay.com/d/vriqwvcvyq56","single_img":"https://thumbcdn.com/snaps/2wuc8tc474vwy4k4.jpg","file_code":"vriqwvcvyq56","length":"00:27:34","views":"1878","vw_fmt":"1.9K","uploaded":"2023-08-22 11:14:54","up_fmt":"22 Agu 2023","up_short":"22 Agu","title":"Bokep Indo Zara Bokong Besar Goyang Wot Zaraaa Montok Semok Tante Dodstream","t_esc":"Bokep Indo Zara Bokong Besar Goyang Wot Zaraaa Montok Semok Tante Dodstream"},{"download_url":"https://myvidplay.com/d/re0lf1c99weg","single_img":"https://thumbcdn.com/snaps/c2r7741nii0hivol.jpg","file_code":"re0lf1c99weg","length":"00:54:52","views":"6935","vw_fmt":"6.9K","uploaded":"2023-08-22 11:14:53","up_fmt":"22 Agu 2023","up_short":"22 Agu","title":"Bokep Indo Toket Kak Zara Momoka Idaman Mango Zaraaa Montok Semok Tante","t_esc":"Bokep Indo Toket Kak Zara Momoka Idaman Mango Zaraaa Montok Semok Tante"},{"download_url":"https://myvidplay.com/d/cs03itw4uja4","single_img":"https://thumbcdn.com/snaps/s4j5wlkchlc8fa4s.jpg","file_code":"cs03itw4uja4","length":"00:12:14","views":"15922","vw_fmt":"15.9K","uploaded":"2023-08-22 11:14:53","up_fmt":"22 Agu 2023","up_short":"22 Agu","title":"Bokep Indo Zara Ebot Mendesah Remas Payudara Zaraaa Montok Semok Tante Dood","t_esc":"Bokep Indo Zara Ebot Mendesah Remas Payudara Zaraaa Montok Semok Tante Dood"},{"download_url":"https://myvidplay.com/d/u0b1cqvvpcal","single_img":"https://thumbcdn.com/snaps/x8fa08x35kcun82j.jpg","file_code":"u0b1cqvvpcal","length":"00:20:43","views":"14317","vw_fmt":"14.3K","uploaded":"2023-08-22 11:14:49","up_fmt":"22 Agu 2023","up_short":"22 Agu","title":"Bokep Indo Zara Cantik Nungging Montok Semok Zaraaa Tante Bokepsin Simintok Yakwad","t_esc":"Bokep Indo Zara Cantik Nungging Montok Semok Zaraaa Tante Bokepsin Simintok Yakwad"},{"download_url":"https://myvidplay.com/d/61ilqa5ux244","single_img":"https://thumbcdn.com/snaps/pysadl8z2mphdank.jpg","file_code":"61ilqa5ux244","length":"01:44:37","views":"22580","vw_fmt":"22.6K","uploaded":"2023-08-22 11:14:48","up_fmt":"22 Agu 2023","up_short":"22 Agu","title":"Bokep Indo Momoka Zara Mango Semok Bohay Binal Zaraaa Montok Tante","t_esc":"Bokep Indo Momoka Zara Mango Semok Bohay Binal Zaraaa Montok Tante"},{"download_url":"https://myvidplay.com/d/yaq59xpdb7gy","single_img":"https://thumbcdn.com/snaps/tx2kkkivessd034s.jpg","file_code":"yaq59xpdb7gy","length":"00:18:32","views":"4988","vw_fmt":"5.0K","uploaded":"2023-08-22 11:14:47","up_fmt":"22 Agu 2023","up_short":"22 Agu","title":"Bokep Indo Miss Zara Beha Hitam Ebot Montok Zaraaa Semok Tante","t_esc":"Bokep Indo Miss Zara Beha Hitam Ebot Montok Zaraaa Semok Tante"},{"download_url":"https://myvidplay.com/d/lgcok8b6lqxo","single_img":"https://thumbcdn.com/snaps/thi22kh3bxqxodxh.jpg","file_code":"lgcok8b6lqxo","length":"00:39:06","views":"10824","vw_fmt":"10.8K","uploaded":"2023-08-22 11:14:46","up_fmt":"22 Agu 2023","up_short":"22 Agu","title":"Bokep Indo Miss Zaraaa Semok Goyang Pantat Besar Montok Tante","t_esc":"Bokep Indo Miss Zaraaa Semok Goyang Pantat Besar Montok Tante"},{"download_url":"https://myvidplay.com/d/myab6cfnk27z","single_img":"https://thumbcdn.com/snaps/ubitwjd78vpatv09.jpg","file_code":"myab6cfnk27z","length":"00:03:53","views":"3266","vw_fmt":"3.3K","uploaded":"2023-08-22 11:14:42","up_fmt":"22 Agu 2023","up_short":"22 Agu","title":"Bokep Indo Ngentot Crot Di Memek Tante Tobrut Hhh Maskkim Onlyfa Website","t_esc":"Bokep Indo Ngentot Crot Di Memek Tante Tobrut Hhh Maskkim Onlyfa Website"},{"download_url":"https://myvidplay.com/d/iq8nxalsyhkb","single_img":"https://thumbcdn.com/snaps/y2q16c4ouin53vuq.jpg","file_code":"iq8nxalsyhkb","length":"00:29:57","views":"5410","vw_fmt":"5.4K","uploaded":"2023-08-22 11:14:40","up_fmt":"22 Agu 2023","up_short":"22 Agu","title":"Bokep Indo Moy Montok Ngewe Cosplay Bling Bebbymoy Tante Semok","t_esc":"Bokep Indo Moy Montok Ngewe Cosplay Bling Bebbymoy Tante Semok"},{"download_url":"https://myvidplay.com/d/99oxm0y106p2","single_img":"https://thumbcdn.com/snaps/iadsb2236m7b86s7.jpg","file_code":"99oxm0y106p2","length":"00:01:52","views":"52169","vw_fmt":"52.2K","uploaded":"2023-08-22 11:14:39","up_fmt":"22 Agu 2023","up_short":"22 Agu","title":"Muasin Bini Tetangga Semok Sotwe Staklam Asupan Viral Pejuang Lendir Links","t_esc":"Muasin Bini Tetangga Semok Sotwe Staklam Asupan Viral Pejuang Lendir Links"},{"download_url":"https://myvidplay.com/d/1s7hswvl7u8o","single_img":"https://thumbcdn.com/snaps/mb73812nau3pztja.jpg","file_code":"1s7hswvl7u8o","length":"00:06:55","views":"1430","vw_fmt":"1.4K","uploaded":"2023-08-22 11:14:36","up_fmt":"22 Agu 2023","up_short":"22 Agu","title":"Bokep Indo Ngentot Crot Di Memek Tante Tobrut Hhh Maskkim Onlyfans Montok","t_esc":"Bokep Indo Ngentot Crot Di Memek Tante Tobrut Hhh Maskkim Onlyfans Montok"},{"download_url":"https://myvidplay.com/d/p0knv61uxvtm","single_img":"https://thumbcdn.com/snaps/82d7uqfzrnwpqgln.jpg","file_code":"p0knv61uxvtm","length":"01:00:00","views":"7093","vw_fmt":"7.1K","uploaded":"2023-08-22 11:14:36","up_fmt":"22 Agu 2023","up_short":"22 Agu","title":"Bokep Indo Ayang Montok Ngentot Wot Live Miss Ay Tante Semok Dood","t_esc":"Bokep Indo Ayang Montok Ngentot Wot Live Miss Ay Tante Semok Dood"},{"download_url":"https://myvidplay.com/d/dyezp6vzkapy","single_img":"https://thumbcdn.com/snaps/omcb04c7056auruo.jpg","file_code":"dyezp6vzkapy","length":"00:13:07","views":"16593","vw_fmt":"16.6K","uploaded":"2023-08-22 11:14:31","up_fmt":"22 Agu 2023","up_short":"22 Agu","title":"Mom Beautiffull Body Goal Tante Bunga Semok Montok Live Masakk Sambil Karaoke","t_esc":"Mom Beautiffull Body Goal Tante Bunga Semok Montok Live Masakk Sambil Karaoke"},{"download_url":"https://myvidplay.com/d/yvlnsvtscaor","single_img":"https://thumbcdn.com/snaps/8v59oe4885rtedzh.jpg","file_code":"yvlnsvtscaor","length":"00:49:03","views":"2065","vw_fmt":"2.1K","uploaded":"2023-08-22 11:14:30","up_fmt":"22 Agu 2023","up_short":"22 Agu","title":"Bokep Milf Ava Addams Titty Fucked And Creampied Tante Montok Semok","t_esc":"Bokep Milf Ava Addams Titty Fucked And Creampied Tante Montok Semok"},{"download_url":"https://myvidplay.com/d/7fz8w59xqbg9","single_img":"https://thumbcdn.com/snaps/ko7m58j51f4rxtan.jpg","file_code":"7fz8w59xqbg9","length":"00:10:11","views":"2671","vw_fmt":"2.7K","uploaded":"2023-08-22 11:14:29","up_fmt":"22 Agu 2023","up_short":"22 Agu","title":"Tante Jones Toket Gede Pink Martha Semok Montok Indonesia Terabox Bokep31 Viral","t_esc":"Tante Jones Toket Gede Pink Martha Semok Montok Indonesia Terabox Bokep31 Viral"},{"download_url":"https://myvidplay.com/d/oj7p5tcusgrv","single_img":"https://thumbcdn.com/snaps/mz0llovw8ig407iv.jpg","file_code":"oj7p5tcusgrv","length":"00:21:46","views":"4079","vw_fmt":"4.1K","uploaded":"2023-08-22 11:14:10","up_fmt":"22 Agu 2023","up_short":"22 Agu","title":"Betty Payudara Jumbo Live Martha Jones Tante Semok Montok Indo Simintok Popstream","t_esc":"Betty Payudara Jumbo Live Martha Jones Tante Semok Montok Indo Simintok Popstream"},{"download_url":"https://myvidplay.com/d/winpesmwu2me","single_img":"https://thumbcdn.com/snaps/5t0vn4sg6qlqdvyj.jpg","file_code":"winpesmwu2me","length":"00:12:10","views":"838","vw_fmt":"838","uploaded":"2023-08-22 11:14:10","up_fmt":"22 Agu 2023","up_short":"22 Agu","title":"Toket Gede Brutal Miss Betty Martha Jones Tante Semok Montok Update Streaming","t_esc":"Toket Gede Brutal Miss Betty Martha Jones Tante Semok Montok Update Streaming"},{"download_url":"https://myvidplay.com/d/kjxl9donufu3","single_img":"https://thumbcdn.com/snaps/2u4qo9gqp6rhkryo.jpg","file_code":"kjxl9donufu3","length":"00:05:13","views":"2201","vw_fmt":"2.2K","uploaded":"2023-08-22 11:13:54","up_fmt":"22 Agu 2023","up_short":"22 Agu","title":"Jones Mango Live Omek Dood Stream Xpanas Video Indo Telegram Asupan Jilbab","t_esc":"Jones Mango Live Omek Dood Stream Xpanas Video Indo Telegram Asupan Jilbab"},{"download_url":"https://myvidplay.com/d/mmie0wsqlpw2","single_img":"https://thumbcdn.com/snaps/wqgjpv6bvgke071k.jpg","file_code":"mmie0wsqlpw2","length":"00:39:05","views":"730","vw_fmt":"730","uploaded":"2023-08-22 11:13:52","up_fmt":"22 Agu 2023","up_short":"22 Agu","title":"Betty Jones Dood Stream Bokepsin Links Streaming Bokep Doods Pro","t_esc":"Betty Jones Dood Stream Bokepsin Links Streaming Bokep Doods Pro"},{"download_url":"https://myvidplay.com/d/dexip1dvy3xs","single_img":"https://thumbcdn.com/snaps/3vycpi6c8772mu2w.jpg","file_code":"dexip1dvy3xs","length":"00:08:06","views":"6814","vw_fmt":"6.8K","uploaded":"2023-08-22 11:13:25","up_fmt":"22 Agu 2023","up_short":"22 Agu","title":"Jeslyn No Topeng Show Colmek Sampai Squirt Di Kamar Mandi Dood Stream","t_esc":"Jeslyn No Topeng Show Colmek Sampai Squirt Di Kamar Mandi Dood Stream"},{"download_url":"https://myvidplay.com/d/wycr26czkngm","single_img":"https://thumbcdn.com/snaps/9sxdjjrb2pkg3epw.jpg","file_code":"wycr26czkngm","length":"00:29:03","views":"591","vw_fmt":"591","uploaded":"2023-08-22 11:13:00","up_fmt":"22 Agu 2023","up_short":"22 Agu","title":"Jeslyn Cantik Erocafe Net Doodstreem Asupan Video Viral Yakwad Memeksiana","t_esc":"Jeslyn Cantik Erocafe Net Doodstreem Asupan Video Viral Yakwad Memeksiana"},{"download_url":"https://myvidplay.com/d/jwtnhbqzksc0","single_img":"https://thumbcdn.com/snaps/kv6xxbuci2jdqr5n.jpg","file_code":"jwtnhbqzksc0","length":"00:29:33","views":"1116","vw_fmt":"1.1K","uploaded":"2023-08-22 11:12:32","up_fmt":"22 Agu 2023","up_short":"22 Agu","title":"Live Show Ml Pagi Host Jeslyn Video Colmek Telegram Website Asupan Dodstream","t_esc":"Live Show Ml Pagi Host Jeslyn Video Colmek Telegram Website Asupan Dodstream"},{"download_url":"https://myvidplay.com/d/dwen5an2lm8b","single_img":"https://thumbcdn.com/snaps/vsjwrjygucj46sop.jpg","file_code":"dwen5an2lm8b","length":"00:42:35","views":"3581","vw_fmt":"3.6K","uploaded":"2023-08-22 11:12:29","up_fmt":"22 Agu 2023","up_short":"22 Agu","title":"Jeslyn Pagi Udah Ngentot Aja Di Bling Yakwad Bokepin Asupan Bokep Video","t_esc":"Jeslyn Pagi Udah Ngentot Aja Di Bling Yakwad Bokepin Asupan Bokep Video"},{"download_url":"https://myvidplay.com/d/vontxdbtu5et","single_img":"https://thumbcdn.com/snaps/igeqan771fah8gsw.jpg","file_code":"vontxdbtu5et","length":"01:30:45","views":"4154","vw_fmt":"4.2K","uploaded":"2023-08-22 11:11:54","up_fmt":"22 Agu 2023","up_short":"22 Agu","title":"X Tante Liadani Ngentot Omek Anal Longdur Play Bokep Doodstreem Dood Tele","t_esc":"X Tante Liadani Ngentot Omek Anal Longdur Play Bokep Doodstreem Dood Tele"},{"download_url":"https://myvidplay.com/d/y3icqcg7fpl7","single_img":"https://thumbcdn.com/snaps/ae8dfjdrvymdvysg.jpg","file_code":"y3icqcg7fpl7","length":"00:49:37","views":"6231","vw_fmt":"6.2K","uploaded":"2023-08-22 11:11:54","up_fmt":"22 Agu 2023","up_short":"22 Agu","title":"X Mbak Liadani Kasih Jatah Ojol Ngewe Prank Play Bokep Tobrut Bokepsin","t_esc":"X Mbak Liadani Kasih Jatah Ojol Ngewe Prank Play Bokep Tobrut Bokepsin"},{"download_url":"https://myvidplay.com/d/zw4u3a2k6unf","single_img":"https://thumbcdn.com/snaps/v578fmw6ve2reo2e.jpg","file_code":"zw4u3a2k6unf","length":"00:12:16","views":"18612","vw_fmt":"18.6K","uploaded":"2023-08-22 11:11:43","up_fmt":"22 Agu 2023","up_short":"22 Agu","title":"Tante Toge Colmek Sampe Squirt Bikin Nagih Bokep Indo Dood Tele Tiktok","t_esc":"Tante Toge Colmek Sampe Squirt Bikin Nagih Bokep Indo Dood Tele Tiktok"},{"download_url":"https://myvidplay.com/d/mp4vo07t5wxb","single_img":"https://thumbcdn.com/snaps/68i2zwe336e34i33.jpg","file_code":"mp4vo07t5wxb","length":"00:19:25","views":"3279","vw_fmt":"3.3K","uploaded":"2023-08-22 11:11:38","up_fmt":"22 Agu 2023","up_short":"22 Agu","title":"Bokep Liadani Colmek Sampai Becek Setelah Gak Puas Ngewe Play Video Viral","t_esc":"Bokep Liadani Colmek Sampai Becek Setelah Gak Puas Ngewe Play Video Viral"},{"download_url":"https://myvidplay.com/d/37n15nkmwwi9","single_img":"https://thumbcdn.com/snaps/4kl5vnbwt93yxgf5.jpg","file_code":"37n15nkmwwi9","length":"00:55:23","views":"8839","vw_fmt":"8.8K","uploaded":"2023-08-22 11:11:36","up_fmt":"22 Agu 2023","up_short":"22 Agu","title":"Bokep Indo Miss Pascol Liadani Dildo Mesin Sampe Crot Telegram Cilbo Doods","t_esc":"Bokep Indo Miss Pascol Liadani Dildo Mesin Sampe Crot Telegram Cilbo Doods"},{"download_url":"https://myvidplay.com/d/vzx519oamu5f","single_img":"https://thumbcdn.com/snaps/00as23e1ntu8npe7.jpg","file_code":"vzx519oamu5f","length":"00:48:01","views":"4762","vw_fmt":"4.8K","uploaded":"2023-08-22 11:09:35","up_fmt":"22 Agu 2023","up_short":"22 Agu","title":"Liadani Prank Ojol Trisome Lg Link Web Dood Bokepsin Ngentot Full Album","t_esc":"Liadani Prank Ojol Trisome Lg Link Web Dood Bokepsin Ngentot Full Album"},{"download_url":"https://myvidplay.com/d/w4ivxg0vk31g","single_img":"https://thumbcdn.com/snaps/erupdp0n6btvxtlf.jpg","file_code":"w4ivxg0vk31g","length":"00:07:15","views":"2485","vw_fmt":"2.5K","uploaded":"2023-08-22 11:09:19","up_fmt":"22 Agu 2023","up_short":"22 Agu","title":"Liadani Juni Part Dood Stream Telegram Doodsflix Link Web Folder Cilbo","t_esc":"Liadani Juni Part Dood Stream Telegram Doodsflix Link Web Folder Cilbo"},{"download_url":"https://myvidplay.com/d/1m4rnltmb5zp","single_img":"https://thumbcdn.com/snaps/euuzjm6e18hl3q9d.jpg","file_code":"1m4rnltmb5zp","length":"00:52:29","views":"4015","vw_fmt":"4.0K","uploaded":"2023-08-22 11:09:13","up_fmt":"22 Agu 2023","up_short":"22 Agu","title":"Bokep Indo Liadani Live Prank Ojol Miss Pascol Video Colmek Doodstream Twitter","t_esc":"Bokep Indo Liadani Live Prank Ojol Miss Pascol Video Colmek Doodstream Twitter"},{"download_url":"https://myvidplay.com/d/n9cisleucgd2","single_img":"https://thumbcdn.com/snaps/5lxrioderiucw8cy.jpg","file_code":"n9cisleucgd2","length":"00:52:29","views":"4561","vw_fmt":"4.6K","uploaded":"2023-08-22 11:09:13","up_fmt":"22 Agu 2023","up_short":"22 Agu","title":"Bokep Indo Liadani Live Prank Ojol Bokepsin Dood Pemersatu Doodflix Bochiel Indonesia","t_esc":"Bokep Indo Liadani Live Prank Ojol Bokepsin Dood Pemersatu Doodflix Bochiel Indonesia"},{"download_url":"https://myvidplay.com/d/vnrp1qr1nonf","single_img":"https://thumbcdn.com/snaps/tqmn7ml8tnoo7h15.jpg","file_code":"vnrp1qr1nonf","length":"00:40:43","views":"5790","vw_fmt":"5.8K","uploaded":"2023-08-22 11:09:08","up_fmt":"22 Agu 2023","up_short":"22 Agu","title":"Mlive Liadani Prank Ojol Kimcilonly Videos Telegram Terupdate Folder Viral","t_esc":"Mlive Liadani Prank Ojol Kimcilonly Videos Telegram Terupdate Folder Viral"},{"download_url":"https://myvidplay.com/d/tn80u53yx0ci","single_img":"https://thumbcdn.com/snaps/u8c6rxy7u282ssl9.jpg","file_code":"tn80u53yx0ci","length":"00:38:01","views":"1942","vw_fmt":"1.9K","uploaded":"2023-08-22 11:08:59","up_fmt":"22 Agu 2023","up_short":"22 Agu","title":"Ayuk Geterin Liadani Ampe Muncratt Kuyy Dood Tele Update Indo Yakwad Simontok","t_esc":"Ayuk Geterin Liadani Ampe Muncratt Kuyy Dood Tele Update Indo Yakwad Simontok"},{"download_url":"https://myvidplay.com/d/u0qrjj112sr5","single_img":"https://thumbcdn.com/snaps/fp92g1hysdpd1wma.jpg","file_code":"u0qrjj112sr5","length":"00:04:48","views":"5673","vw_fmt":"5.7K","uploaded":"2023-08-22 11:08:57","up_fmt":"22 Agu 2023","up_short":"22 Agu","title":"Liadani Mesin Baru Langsung Crot Dood Stream Viral Tele Cantik Tobrut Sotwe","t_esc":"Liadani Mesin Baru Langsung Crot Dood Stream Viral Tele Cantik Tobrut Sotwe"},{"download_url":"https://myvidplay.com/d/qkazitu7ocj9","single_img":"https://thumbcdn.com/snaps/6py6t0pvhbumimkx.jpg","file_code":"qkazitu7ocj9","length":"00:40:43","views":"9167","vw_fmt":"9.2K","uploaded":"2023-08-22 11:08:55","up_fmt":"22 Agu 2023","up_short":"22 Agu","title":"Liadani Prank Ojol Lagi Xpanas Videos Ngentot Viral Live","t_esc":"Liadani Prank Ojol Lagi Xpanas Videos Ngentot Viral Live"},{"download_url":"https://myvidplay.com/d/x2p2g6wikr3p","single_img":"https://thumbcdn.com/snaps/ylp8s7du1qjvci2w.jpg","file_code":"x2p2g6wikr3p","length":"00:11:24","views":"4127","vw_fmt":"4.1K","uploaded":"2023-08-22 11:08:52","up_fmt":"22 Agu 2023","up_short":"22 Agu","title":"Liadani Prank Ngentot Threesome Jilbab Bokep Dood Staklam Doodstream Bokep31","t_esc":"Liadani Prank Ngentot Threesome Jilbab Bokep Dood Staklam Doodstream Bokep31"},{"download_url":"https://myvidplay.com/d/wlkty5w5qnly","single_img":"https://thumbcdn.com/snaps/xfblgs361hezk1rp.jpg","file_code":"wlkty5w5qnly","length":"00:29:22","views":"1825","vw_fmt":"1.8K","uploaded":"2023-08-22 11:08:46","up_fmt":"22 Agu 2023","up_short":"22 Agu","title":"Tante Liadani Maenan Mesin Sodok Mulut Annl Bokepsatset Links Website Terupdate Bochiel","t_esc":"Tante Liadani Maenan Mesin Sodok Mulut Annl Bokepsatset Links Website Terupdate Bochiel"},{"download_url":"https://myvidplay.com/d/s4ax4hc6txpq","single_img":"https://thumbcdn.com/snaps/j9kt1sxcgg9n2esm.jpg","file_code":"s4ax4hc6txpq","length":"00:38:02","views":"1947","vw_fmt":"1.9K","uploaded":"2023-08-22 11:08:42","up_fmt":"22 Agu 2023","up_short":"22 Agu","title":"Ayuk Geterin Liadani Ampe Muncratt Kuyy Doods Pro Video Viral Telegram Indo","t_esc":"Ayuk Geterin Liadani Ampe Muncratt Kuyy Doods Pro Video Viral Telegram Indo"},{"download_url":"https://myvidplay.com/d/pi8f7uekd1e9","single_img":"https://thumbcdn.com/snaps/qfgsco07llpysvsz.jpg","file_code":"pi8f7uekd1e9","length":"00:29:22","views":"2213","vw_fmt":"2.2K","uploaded":"2023-08-22 11:08:40","up_fmt":"22 Agu 2023","up_short":"22 Agu","title":"Tante Liadani Maenan Mesin Sodok Mulut Annl Dood Stream Viral Yakwad Pejuang","t_esc":"Tante Liadani Maenan Mesin Sodok Mulut Annl Dood Stream Viral Yakwad Pejuang"},{"download_url":"https://myvidplay.com/d/wq3kwmnjclia","single_img":"https://thumbcdn.com/snaps/tozagl4a6m68b200.jpg","file_code":"wq3kwmnjclia","length":"00:38:02","views":"5825","vw_fmt":"5.8K","uploaded":"2023-08-22 11:08:39","up_fmt":"22 Agu 2023","up_short":"22 Agu","title":"Ayuk Geterin Liadani Ampe Muncratt Kuyy Simintok Ngentot Bokep Video Update Twitter","t_esc":"Ayuk Geterin Liadani Ampe Muncratt Kuyy Simintok Ngentot Bokep Video Update Twitter"},{"download_url":"https://myvidplay.com/d/uwen659gccg2","single_img":"https://thumbcdn.com/snaps/nrxn7wy8xon6d0hz.jpg","file_code":"uwen659gccg2","length":"00:53:28","views":"5615","vw_fmt":"5.6K","uploaded":"2023-08-22 11:08:30","up_fmt":"22 Agu 2023","up_short":"22 Agu","title":"Liadani Mekinya Lawan Mesin Dood Stream Ful Album Viral Doodflix Indonesia Asupan","t_esc":"Liadani Mekinya Lawan Mesin Dood Stream Ful Album Viral Doodflix Indonesia Asupan"},{"download_url":"https://myvidplay.com/d/yu31yson2g0g","single_img":"https://thumbcdn.com/snaps/a2ijli2dqzr0vrov.jpg","file_code":"yu31yson2g0g","length":"00:52:29","views":"4010","vw_fmt":"4.0K","uploaded":"2023-08-22 11:08:27","up_fmt":"22 Agu 2023","up_short":"22 Agu","title":"Bokep Indo Liadani Live Prank Ojol Viral Telegram Links Ngentot Dodstream","t_esc":"Bokep Indo Liadani Live Prank Ojol Viral Telegram Links Ngentot Dodstream"},{"download_url":"https://myvidplay.com/d/3hs5ohw8rz8t","single_img":"https://thumbcdn.com/snaps/ul762i1rcvu2xhzz.jpg","file_code":"3hs5ohw8rz8t","length":"00:07:25","views":"6122","vw_fmt":"6.1K","uploaded":"2023-08-22 11:06:46","up_fmt":"22 Agu 2023","up_short":"22 Agu","title":"Bebby Moy Yg Viral Lulustream Bokepsin Video Indo Live Staklam","t_esc":"Bebby Moy Yg Viral Lulustream Bokepsin Video Indo Live Staklam"},{"download_url":"https://myvidplay.com/d/1h9nn4998vif","single_img":"https://thumbcdn.com/snaps/cm2mmbotl4ifhos2.jpg","file_code":"1h9nn4998vif","length":"00:10:16","views":"3881","vw_fmt":"3.9K","uploaded":"2023-08-22 11:06:23","up_fmt":"22 Agu 2023","up_short":"22 Agu","title":"Moy Live Bar Folder Doodsflix Sotwe Bokepind Dodstream","t_esc":"Moy Live Bar Folder Doodsflix Sotwe Bokepind Dodstream"},{"download_url":"https://myvidplay.com/d/v0on1c6yvmh1","single_img":"https://thumbcdn.com/snaps/k3hwkdavcpdjvh39.jpg","file_code":"v0on1c6yvmh1","length":"00:35:55","views":"4211","vw_fmt":"4.2K","uploaded":"2023-08-22 11:06:21","up_fmt":"22 Agu 2023","up_short":"22 Agu","title":"Moy Toge Bebasindo Xpanas Telegram Sotwe Doodflix","t_esc":"Moy Toge Bebasindo Xpanas Telegram Sotwe Doodflix"},{"download_url":"https://myvidplay.com/d/1bxerw8998m8","single_img":"https://thumbcdn.com/snaps/swuk2etbr7lkojlt.jpg","file_code":"1bxerw8998m8","length":"00:14:50","views":"4734","vw_fmt":"4.7K","uploaded":"2023-08-22 11:06:11","up_fmt":"22 Agu 2023","up_short":"22 Agu","title":"Bebby Moy Berurut Bokepsatset Video Bokep Simontok Telegram Poophd","t_esc":"Bebby Moy Berurut Bokepsatset Video Bokep Simontok Telegram Poophd"},{"download_url":"https://myvidplay.com/d/9a1sv27ixgxc","single_img":"https://thumbcdn.com/snaps/ztttsdz1olp3vjfe.jpg","file_code":"9a1sv27ixgxc","length":"01:35:02","views":"12750","vw_fmt":"12.8K","uploaded":"2023-08-22 11:05:42","up_fmt":"22 Agu 2023","up_short":"22 Agu","title":"Beby Moy Ngentot Sama Pacarnya Enak Banget Genjotanya Video Colmek Update Doostream","t_esc":"Beby Moy Ngentot Sama Pacarnya Enak Banget Genjotanya Video Colmek Update Doostream"},{"download_url":"https://myvidplay.com/d/71zx48naejz5","single_img":"https://thumbcdn.com/snaps/jdhkp4vgm5b661cn.jpg","file_code":"71zx48naejz5","length":"00:29:57","views":"19182","vw_fmt":"19.2K","uploaded":"2023-08-22 11:05:38","up_fmt":"22 Agu 2023","up_short":"22 Agu","title":"Bokep Indo Moy Montok Ngewe Cosplay Bling Bebbymoy Tante Semok","t_esc":"Bokep Indo Moy Montok Ngewe Cosplay Bling Bebbymoy Tante Semok"},{"download_url":"https://myvidplay.com/d/g5a1hdt8ouks","single_img":"https://thumbcdn.com/snaps/3uyqvopgh2cb2gx2.jpg","file_code":"g5a1hdt8ouks","length":"00:52:39","views":"11420","vw_fmt":"11.4K","uploaded":"2023-08-22 11:05:32","up_fmt":"22 Agu 2023","up_short":"22 Agu","title":"Moy Crott Dimulut Makin Gede Aja Toketnya Doodstreem Tele Toketbagus Link Web","t_esc":"Moy Crott Dimulut Makin Gede Aja Toketnya Doodstreem Tele Toketbagus Link Web"},{"download_url":"https://myvidplay.com/d/tkrmszca40sl","single_img":"https://thumbcdn.com/snaps/q00dp2ucmcqmdref.jpg","file_code":"tkrmszca40sl","length":"00:07:11","views":"6214","vw_fmt":"6.2K","uploaded":"2023-08-22 11:05:29","up_fmt":"22 Agu 2023","up_short":"22 Agu","title":"Bokep Indo Bebymoy Tobrut Pakai Hijab Sange Colmek Moy Bebbymoy Tele Pekoblive","t_esc":"Bokep Indo Bebymoy Tobrut Pakai Hijab Sange Colmek Moy Bebbymoy Tele Pekoblive"},{"download_url":"https://myvidplay.com/d/92pqewkx1ko3","single_img":"https://thumbcdn.com/snaps/6rhp14er64cwthi8.jpg","file_code":"92pqewkx1ko3","length":"00:20:55","views":"3230","vw_fmt":"3.2K","uploaded":"2023-08-22 11:04:37","up_fmt":"22 Agu 2023","up_short":"22 Agu","title":"Kak Miyubi Pamerin Toket Mulus Pantat Semok Bokepsin Tiktok Full Album Videos","t_esc":"Kak Miyubi Pamerin Toket Mulus Pantat Semok Bokepsin Tiktok Full Album Videos"},{"download_url":"https://myvidplay.com/d/oh5mol5ndgy0","single_img":"https://thumbcdn.com/snaps/s6lmn0327rx9d52h.jpg","file_code":"oh5mol5ndgy0","length":"01:00:00","views":"1399","vw_fmt":"1.4K","uploaded":"2023-08-22 11:04:33","up_fmt":"22 Agu 2023","up_short":"22 Agu","title":"Goyang Erotis Miyoubee Telanjang Dada Di Dream Live Dood Stream Bokep Video","t_esc":"Goyang Erotis Miyoubee Telanjang Dada Di Dream Live Dood Stream Bokep Video"},{"download_url":"https://myvidplay.com/d/cj8bu32axi0g","single_img":"https://thumbcdn.com/snaps/9224o0jyrncwygry.jpg","file_code":"cj8bu32axi0g","length":"00:09:44","views":"9074","vw_fmt":"9.1K","uploaded":"2023-08-22 11:04:18","up_fmt":"22 Agu 2023","up_short":"22 Agu","title":"Kakak Body Mantep Kepunyaan Becek Toketbagus Lokal Doodsflix Pemersatu Sotwe","t_esc":"Kakak Body Mantep Kepunyaan Becek Toketbagus Lokal Doodsflix Pemersatu Sotwe"},{"download_url":"https://myvidplay.com/d/mvugo9sy9fvu","single_img":"https://thumbcdn.com/snaps/et42vpfb8syjvpvx.jpg","file_code":"mvugo9sy9fvu","length":"00:10:20","views":"1791","vw_fmt":"1.8K","uploaded":"2023-08-22 11:04:16","up_fmt":"22 Agu 2023","up_short":"22 Agu","title":"Miyoubee Dream Live Host Paling Hot Pemersatu Dodstream Jilbab Telegram Bochiel","t_esc":"Miyoubee Dream Live Host Paling Hot Pemersatu Dodstream Jilbab Telegram Bochiel"},{"download_url":"https://myvidplay.com/d/e6rfmhqgro4f","single_img":"https://thumbcdn.com/snaps/qtw2lmth2xvesgy0.jpg","file_code":"e6rfmhqgro4f","length":"00:28:54","views":"1460","vw_fmt":"1.5K","uploaded":"2023-08-22 11:04:08","up_fmt":"22 Agu 2023","up_short":"22 Agu","title":"Miyoubee Dreamlive Om K M Ncu Rrr Doostream Doods Pro Terabox Telegram","t_esc":"Miyoubee Dreamlive Om K M Ncu Rrr Doostream Doods Pro Terabox Telegram"},{"download_url":"https://myvidplay.com/d/vmx1ck6i1hw4","single_img":"https://thumbcdn.com/snaps/nxhhbb9mmmnuralo.jpg","file_code":"vmx1ck6i1hw4","length":"00:19:58","views":"1457","vw_fmt":"1.5K","uploaded":"2023-08-22 11:04:07","up_fmt":"22 Agu 2023","up_short":"22 Agu","title":"Jembut Masih Lebat Kak Miyoubee Dream Live Bugil Sh Streaming Ngentot Website","t_esc":"Jembut Masih Lebat Kak Miyoubee Dream Live Bugil Sh Streaming Ngentot Website"},{"download_url":"https://myvidplay.com/d/8h77cdw2bn7y","single_img":"https://thumbcdn.com/snaps/7y6dkyy69i5dng8d.jpg","file_code":"8h77cdw2bn7y","length":"00:56:33","views":"2344","vw_fmt":"2.3K","uploaded":"2023-08-22 03:07:43","up_fmt":"22 Agu 2023","up_short":"22 Agu","title":"Cosplay Jadi Siswi Cewek Sma Nakal Menggoda Penonton Terabox Live Simontok Video","t_esc":"Cosplay Jadi Siswi Cewek Sma Nakal Menggoda Penonton Terabox Live Simontok Video"},{"download_url":"https://myvidplay.com/d/i7zsj3mxp1h9","single_img":"https://thumbcdn.com/snaps/9tu8s1s2icedt6ye.jpg","file_code":"i7zsj3mxp1h9","length":"00:15:50","views":"9837","vw_fmt":"9.8K","uploaded":"2023-08-22 03:06:21","up_fmt":"22 Agu 2023","up_short":"22 Agu","title":"Video Bokep Freya Cosplay Anak Sma Di Culik Link Web Bokepind Memeksiana","t_esc":"Video Bokep Freya Cosplay Anak Sma Di Culik Link Web Bokepind Memeksiana"},{"download_url":"https://myvidplay.com/d/hg9e9urjy4p6","single_img":"https://thumbcdn.com/snaps/80cedraa2u5mzkis.jpg","file_code":"hg9e9urjy4p6","length":"00:08:44","views":"13017","vw_fmt":"13.0K","uploaded":"2023-08-21 17:34:03","up_fmt":"21 Agu 2023","up_short":"21 Agu","title":"Bokep Indo Msbreewc Awalnya Pijat Berakhir Ngentot Bokepsin Com Toketbagus Doods Pro","t_esc":"Bokep Indo Msbreewc Awalnya Pijat Berakhir Ngentot Bokepsin Com Toketbagus Doods Pro"},{"download_url":"https://myvidplay.com/d/zyqirjfqu2g0","single_img":"https://thumbcdn.com/snaps/l08cykfkx77d1lie.jpg","file_code":"zyqirjfqu2g0","length":"00:07:15","views":"9122","vw_fmt":"9.1K","uploaded":"2023-08-21 17:33:20","up_fmt":"21 Agu 2023","up_short":"21 Agu","title":"Ngomong Pake Bahasa Indo Konten Chindo Msbreewc Bj In Video Bokepsin Memeksiana","t_esc":"Ngomong Pake Bahasa Indo Konten Chindo Msbreewc Bj In Video Bokepsin Memeksiana"},{"download_url":"https://myvidplay.com/d/0yem3l6v5ll8","single_img":"https://thumbcdn.com/snaps/b2z77q9kqebwv17r.jpg","file_code":"0yem3l6v5ll8","length":"00:04:53","views":"6208","vw_fmt":"6.2K","uploaded":"2023-08-21 17:33:16","up_fmt":"21 Agu 2023","up_short":"21 Agu","title":"Mulus Chindo Ms Breewc Indo Sotwe Xpanas Telegram Tele","t_esc":"Mulus Chindo Ms Breewc Indo Sotwe Xpanas Telegram Tele"},{"download_url":"https://myvidplay.com/d/csg9nthwdx5c","single_img":"https://thumbcdn.com/snaps/3cnvpjmmmbsjg070.jpg","file_code":"csg9nthwdx5c","length":"00:09:36","views":"2992","vw_fmt":"3.0K","uploaded":"2023-08-21 17:33:12","up_fmt":"21 Agu 2023","up_short":"21 Agu","title":"Msbreewc Pakai Kimono Sepong Kontol Ayang Lulustream Downloader Bokep Video Popstream","t_esc":"Msbreewc Pakai Kimono Sepong Kontol Ayang Lulustream Downloader Bokep Video Popstream"},{"download_url":"https://myvidplay.com/d/2lfnimtpykgc","single_img":"https://thumbcdn.com/snaps/iavemtokfcpv43x6.jpg","file_code":"2lfnimtpykgc","length":"00:03:18","views":"2106","vw_fmt":"2.1K","uploaded":"2023-08-21 17:31:02","up_fmt":"21 Agu 2023","up_short":"21 Agu","title":"Msbreewc Show Body Montok Menggoda Popstream Lokal Doods Pro Bochiel Tobrut","t_esc":"Msbreewc Show Body Montok Menggoda Popstream Lokal Doods Pro Bochiel Tobrut"},{"download_url":"https://myvidplay.com/d/ivr1zrbbacg0","single_img":"https://thumbcdn.com/snaps/ybdnkp9661ugatad.jpg","file_code":"ivr1zrbbacg0","length":"00:03:34","views":"1046","vw_fmt":"1.0K","uploaded":"2023-08-21 17:31:02","up_fmt":"21 Agu 2023","up_short":"21 Agu","title":"Service Nikmat Dari Msbreewc Update Popstream Bokepsin Bokepin Yakwad","t_esc":"Service Nikmat Dari Msbreewc Update Popstream Bokepsin Bokepin Yakwad"},{"download_url":"https://myvidplay.com/d/2qwyw1sui63u","single_img":"https://thumbcdn.com/snaps/2yza22it9t251j9y.jpg","file_code":"2qwyw1sui63u","length":"00:11:50","views":"4164","vw_fmt":"4.2K","uploaded":"2023-08-21 17:31:02","up_fmt":"21 Agu 2023","up_short":"21 Agu","title":"Msbreewc Dientot Sambil Telpon Ngewe Bokepind Bokepsin Ful Album Telegram Video Indo","t_esc":"Msbreewc Dientot Sambil Telpon Ngewe Bokepind Bokepsin Ful Album Telegram Video Indo"},{"download_url":"https://myvidplay.com/d/6c2229p8e0uj","single_img":"https://thumbcdn.com/snaps/qlrt16cpjixichzr.jpg","file_code":"6c2229p8e0uj","length":"00:16:32","views":"6923","vw_fmt":"6.9K","uploaded":"2023-08-21 17:31:01","up_fmt":"21 Agu 2023","up_short":"21 Agu","title":"Bokep Msbreewc Kostum Spider Indobokep Downloader Doodstreem Video Indo Dood Bebasindo","t_esc":"Bokep Msbreewc Kostum Spider Indobokep Downloader Doodstreem Video Indo Dood Bebasindo"},{"download_url":"https://myvidplay.com/d/nln9uup3vwpe","single_img":"https://thumbcdn.com/snaps/px5ew5d66qlfvihl.jpg","file_code":"nln9uup3vwpe","length":"00:16:32","views":"2059","vw_fmt":"2.1K","uploaded":"2023-08-21 17:30:59","up_fmt":"21 Agu 2023","up_short":"21 Agu","title":"Cosplay Kostum Msbreewc Stream Telegram Asupan Viral Bokepsin Video Colmek Bokep31","t_esc":"Cosplay Kostum Msbreewc Stream Telegram Asupan Viral Bokepsin Video Colmek Bokep31"},{"download_url":"https://myvidplay.com/d/i6hz62uwyxun","single_img":"https://thumbcdn.com/snaps/wym2rjbbu9a14k13.jpg","file_code":"i6hz62uwyxun","length":"00:16:32","views":"2750","vw_fmt":"2.8K","uploaded":"2023-08-21 17:30:49","up_fmt":"21 Agu 2023","up_short":"21 Agu","title":"Cosplay Kostum Msbreewc Stream Ngentot Tele Streaming Links Viral","t_esc":"Cosplay Kostum Msbreewc Stream Ngentot Tele Streaming Links Viral"},{"download_url":"https://myvidplay.com/d/rs59j5mq44kw","single_img":"https://thumbcdn.com/snaps/touo5ahax0cf4wrc.jpg","file_code":"rs59j5mq44kw","length":"00:01:13","views":"5246","vw_fmt":"5.2K","uploaded":"2023-08-21 17:30:47","up_fmt":"21 Agu 2023","up_short":"21 Agu","title":"Msbreewc Leaked Of Lagi Viral Simontok Doods Pro Doodsflix","t_esc":"Msbreewc Leaked Of Lagi Viral Simontok Doods Pro Doodsflix"},{"download_url":"https://myvidplay.com/d/1ssjxv7a3m0r","single_img":"https://thumbcdn.com/snaps/2k0z40xyk8ufqcht.jpg","file_code":"1ssjxv7a3m0r","length":"00:02:40","views":"7631","vw_fmt":"7.6K","uploaded":"2023-08-21 17:30:47","up_fmt":"21 Agu 2023","up_short":"21 Agu","title":"Only Fans Msbreewc Watch Online Or Download Popstream Terabox Jilbab Video Viral","t_esc":"Only Fans Msbreewc Watch Online Or Download Popstream Terabox Jilbab Video Viral"},{"download_url":"https://myvidplay.com/d/ih4obnr77s2m","single_img":"https://thumbcdn.com/snaps/7x0oi5v4lkxioclj.jpg","file_code":"ih4obnr77s2m","length":"00:01:13","views":"3283","vw_fmt":"3.3K","uploaded":"2023-08-21 17:30:42","up_fmt":"21 Agu 2023","up_short":"21 Agu","title":"Msbreewc Cosplay Suster Jilbab Memeksiana Folder Terupdate Video Viral","t_esc":"Msbreewc Cosplay Suster Jilbab Memeksiana Folder Terupdate Video Viral"},{"download_url":"https://myvidplay.com/d/wfesf552yk8x","single_img":"https://thumbcdn.com/snaps/upcbpihyl21px7pb.jpg","file_code":"wfesf552yk8x","length":"00:02:17","views":"4051","vw_fmt":"4.1K","uploaded":"2023-08-21 17:30:41","up_fmt":"21 Agu 2023","up_short":"21 Agu","title":"Msbreewc Pamer Booty Link Web Doostream Bokep Dood Doodstream Folder","t_esc":"Msbreewc Pamer Booty Link Web Doostream Bokep Dood Doodstream Folder"},{"download_url":"https://myvidplay.com/d/t6y9i7ffiit2","single_img":"https://thumbcdn.com/snaps/kjjtgqwttpm07ef6.jpg","file_code":"t6y9i7ffiit2","length":"00:01:13","views":"1886","vw_fmt":"1.9K","uploaded":"2023-08-21 17:30:40","up_fmt":"21 Agu 2023","up_short":"21 Agu","title":"Msbreewc Cosplay Suster Link Web Telegram Ful Album Links Asupan","t_esc":"Msbreewc Cosplay Suster Link Web Telegram Ful Album Links Asupan"},{"download_url":"https://myvidplay.com/d/7davbw49hez2","single_img":"https://thumbcdn.com/snaps/1lv8046y8xg892sa.jpg","file_code":"7davbw49hez2","length":"00:06:21","views":"5123","vw_fmt":"5.1K","uploaded":"2023-08-21 17:30:39","up_fmt":"21 Agu 2023","up_short":"21 Agu","title":"Paksa Cici Ms Breewc Nyepong Ngewe Di Tangga Sangetube Dood Stream Ful","t_esc":"Paksa Cici Ms Breewc Nyepong Ngewe Di Tangga Sangetube Dood Stream Ful"},{"download_url":"https://myvidplay.com/d/8odu9y989eqv","single_img":"https://thumbcdn.com/snaps/zbnn5e0scx3glhuw.jpg","file_code":"8odu9y989eqv","length":"00:11:11","views":"2697","vw_fmt":"2.7K","uploaded":"2023-08-21 17:26:01","up_fmt":"21 Agu 2023","up_short":"21 Agu","title":"Msbreewc Cosplay Spiderman Full Bokepind Tobrut Doodstream Lokal Tiktok","t_esc":"Msbreewc Cosplay Spiderman Full Bokepind Tobrut Doodstream Lokal Tiktok"},{"download_url":"https://myvidplay.com/d/3vkzm0ff3nm7","single_img":"https://thumbcdn.com/snaps/qnjsi6emgyov0m20.jpg","file_code":"3vkzm0ff3nm7","length":"00:07:49","views":"8382","vw_fmt":"8.4K","uploaded":"2023-08-21 17:25:59","up_fmt":"21 Agu 2023","up_short":"21 Agu","title":"Pov Ketika Anda Punya Istri Cantik Sange An Msbreewc Lokal Doodsflix Bokepind","t_esc":"Pov Ketika Anda Punya Istri Cantik Sange An Msbreewc Lokal Doodsflix Bokepind"},{"download_url":"https://myvidplay.com/d/zxcv2jiof3fm","single_img":"https://thumbcdn.com/snaps/u8q488tbvyqxp1vi.jpg","file_code":"zxcv2jiof3fm","length":"00:19:28","views":"4315","vw_fmt":"4.3K","uploaded":"2023-08-21 17:24:17","up_fmt":"21 Agu 2023","up_short":"21 Agu","title":"Bokep Indo Msbreewc Vcs Sama Koko Bahasa Indonesia Bokepsin Video Colmek Terabox","t_esc":"Bokep Indo Msbreewc Vcs Sama Koko Bahasa Indonesia Bokepsin Video Colmek Terabox"},{"download_url":"https://myvidplay.com/d/pt01m4jqby3z","single_img":"https://thumbcdn.com/snaps/bfdlupmu767e1u47.jpg","file_code":"pt01m4jqby3z","length":"00:06:15","views":"8495","vw_fmt":"8.5K","uploaded":"2023-08-21 17:24:16","up_fmt":"21 Agu 2023","up_short":"21 Agu","title":"Bokep Indo Msbreewc Cosplay Anime Bikin Sange Bokepsin Poophd Dood Lokal Streaming","t_esc":"Bokep Indo Msbreewc Cosplay Anime Bikin Sange Bokepsin Poophd Dood Lokal Streaming"},{"download_url":"https://myvidplay.com/d/n71jx87zutxm","single_img":"https://thumbcdn.com/snaps/c61jedgkyfg06lr8.jpg","file_code":"n71jx87zutxm","length":"00:10:35","views":"4602","vw_fmt":"4.6K","uploaded":"2023-08-21 17:24:15","up_fmt":"21 Agu 2023","up_short":"21 Agu","title":"Bokep Indo Ngentot Ms Breewc Cosplay Spiderman Venom Bokepsin Video Viral Indonesia","t_esc":"Bokep Indo Ngentot Ms Breewc Cosplay Spiderman Venom Bokepsin Video Viral Indonesia"},{"download_url":"https://myvidplay.com/d/iopylsudir0v","single_img":"https://thumbcdn.com/snaps/31k2qx26jen3cgjm.jpg","file_code":"iopylsudir0v","length":"00:05:59","views":"1965","vw_fmt":"2.0K","uploaded":"2023-08-21 17:24:15","up_fmt":"21 Agu 2023","up_short":"21 Agu","title":"Bokep Indo Msbreewc Cindo Sepong Kontol Koko Bokepsin Terabox Bebasindo Doodstreem Terupdate","t_esc":"Bokep Indo Msbreewc Cindo Sepong Kontol Koko Bokepsin Terabox Bebasindo Doodstreem Terupdate"},{"download_url":"https://myvidplay.com/d/pdzv742fhut5","single_img":"https://thumbcdn.com/snaps/hfjli2ziipgusmds.jpg","file_code":"pdzv742fhut5","length":"00:06:50","views":"5665","vw_fmt":"5.7K","uploaded":"2023-08-21 17:24:12","up_fmt":"21 Agu 2023","up_short":"21 Agu","title":"Bokep Indo Msbreewc Kocokin Ayang Sampe Crot Bokepsin Sotwe Staklam Update Bokep31","t_esc":"Bokep Indo Msbreewc Kocokin Ayang Sampe Crot Bokepsin Sotwe Staklam Update Bokep31"},{"download_url":"https://myvidplay.com/d/rip0sx2afz9d","single_img":"https://thumbcdn.com/snaps/afwzvwbxwu5miz8a.jpg","file_code":"rip0sx2afz9d","length":"00:06:01","views":"3032","vw_fmt":"3.0K","uploaded":"2023-08-21 17:24:11","up_fmt":"21 Agu 2023","up_short":"21 Agu","title":"Bokep Indo Msbreewc Cindo Colmek Pake Dildo Jumbo Bokepsin Video Website Asupan","t_esc":"Bokep Indo Msbreewc Cindo Colmek Pake Dildo Jumbo Bokepsin Video Website Asupan"},{"download_url":"https://myvidplay.com/d/aiigdacn4l36","single_img":"https://thumbcdn.com/snaps/fw39siyjh2sxmhes.jpg","file_code":"aiigdacn4l36","length":"00:15:08","views":"4331","vw_fmt":"4.3K","uploaded":"2023-08-21 17:24:10","up_fmt":"21 Agu 2023","up_short":"21 Agu","title":"Bokep Indo Ms Breewc Chindo Sange Dalam Mobil Bokepsin Doodsflix Dood Tele","t_esc":"Bokep Indo Ms Breewc Chindo Sange Dalam Mobil Bokepsin Doodsflix Dood Tele"},{"download_url":"https://myvidplay.com/d/k89rn57qpfvn","single_img":"https://thumbcdn.com/snaps/82cvzkw0c2pu4mc2.jpg","file_code":"k89rn57qpfvn","length":"00:06:33","views":"10559","vw_fmt":"10.6K","uploaded":"2023-08-21 17:24:08","up_fmt":"21 Agu 2023","up_short":"21 Agu","title":"Bokep Indo Msbreewc Cindo Toge Mulus Ngentot Bokepsin Lagi Viral Doods Pro","t_esc":"Bokep Indo Msbreewc Cindo Toge Mulus Ngentot Bokepsin Lagi Viral Doods Pro"},{"download_url":"https://myvidplay.com/d/5aqp62y42agd","single_img":"https://thumbcdn.com/snaps/m83bncnpkjasedjk.jpg","file_code":"5aqp62y42agd","length":"00:06:57","views":"18991","vw_fmt":"19.0K","uploaded":"2023-08-21 17:24:07","up_fmt":"21 Agu 2023","up_short":"21 Agu","title":"Bokep Indo Msbreewc Crotin Memek Cindo Cantik Bokepsin Dood Tele Asupan Viral","t_esc":"Bokep Indo Msbreewc Crotin Memek Cindo Cantik Bokepsin Dood Tele Asupan Viral"},{"download_url":"https://myvidplay.com/d/soaygyolt38f","single_img":"https://thumbcdn.com/snaps/mrkj5plvb115yfbs.jpg","file_code":"soaygyolt38f","length":"00:05:42","views":"4185","vw_fmt":"4.2K","uploaded":"2023-08-21 17:24:06","up_fmt":"21 Agu 2023","up_short":"21 Agu","title":"Bokep Indo Msbreewc Cindo Cantik Ml Wot Bokepsin Doostream Popstream Jilbab Link","t_esc":"Bokep Indo Msbreewc Cindo Cantik Ml Wot Bokepsin Doostream Popstream Jilbab Link"},{"download_url":"https://myvidplay.com/d/fhwmbffth73g","single_img":"https://thumbcdn.com/snaps/3jtxmjkeqlkvhbwv.jpg","file_code":"fhwmbffth73g","length":"00:09:57","views":"2116","vw_fmt":"2.1K","uploaded":"2023-08-21 17:24:03","up_fmt":"21 Agu 2023","up_short":"21 Agu","title":"Msbreewc Pool Sex Of Ngentot Popstream Doods Pro Video Indo Cilbo","t_esc":"Msbreewc Pool Sex Of Ngentot Popstream Doods Pro Video Indo Cilbo"},{"download_url":"https://myvidplay.com/d/eihme0dzgar7","single_img":"https://thumbcdn.com/snaps/m5nbv0e7zcbhtmph.jpg","file_code":"eihme0dzgar7","length":"00:10:43","views":"1709","vw_fmt":"1.7K","uploaded":"2023-08-21 17:24:02","up_fmt":"21 Agu 2023","up_short":"21 Agu","title":"Msbreewc Car Blowjob Of Doodstreem Telegram Cantik Tobrut Viral Lagi","t_esc":"Msbreewc Car Blowjob Of Doodstreem Telegram Cantik Tobrut Viral Lagi"},{"download_url":"https://myvidplay.com/d/27u1tubvy7dm","single_img":"https://thumbcdn.com/snaps/lkemnj8335x5r8q7.jpg","file_code":"27u1tubvy7dm","length":"00:06:15","views":"7161","vw_fmt":"7.2K","uploaded":"2023-08-21 17:24:00","up_fmt":"21 Agu 2023","up_short":"21 Agu","title":"Msbreewc Jadi Cosplayers Jepang Uting Toket Pink Real Bokephub Streamtape Indo Sotwe","t_esc":"Msbreewc Jadi Cosplayers Jepang Uting Toket Pink Real Bokephub Streamtape Indo Sotwe"},{"download_url":"https://myvidplay.com/d/gxoc7t7qmqsx","single_img":"https://thumbcdn.com/snaps/gbmh2bpjlatglu2e.jpg","file_code":"gxoc7t7qmqsx","length":"00:06:01","views":"2240","vw_fmt":"2.2K","uploaded":"2023-08-21 17:23:59","up_fmt":"21 Agu 2023","up_short":"21 Agu","title":"Mirror Sex Bersama Chindo Binal Kak Msbreewc Onlyfans Bokephub Streamtape Bochiel Telegram","t_esc":"Mirror Sex Bersama Chindo Binal Kak Msbreewc Onlyfans Bokephub Streamtape Bochiel Telegram"},{"download_url":"https://myvidplay.com/d/4ouzyiynueqq","single_img":"https://thumbcdn.com/snaps/2uo2pfluhw7wnnf8.jpg","file_code":"4ouzyiynueqq","length":"00:06:57","views":"31078","vw_fmt":"31.1K","uploaded":"2023-08-21 17:23:59","up_fmt":"21 Agu 2023","up_short":"21 Agu","title":"Msbreewc Ketahuan Colmek Sambil Nonton Bokep Terabox Twitter Doodsflix Doodflix","t_esc":"Msbreewc Ketahuan Colmek Sambil Nonton Bokep Terabox Twitter Doodsflix Doodflix"},{"download_url":"https://myvidplay.com/d/ybl0l4qfpmz5","single_img":"https://thumbcdn.com/snaps/s7eg7qih5od1itvy.jpg","file_code":"ybl0l4qfpmz5","length":"00:17:39","views":"5909","vw_fmt":"5.9K","uploaded":"2023-08-21 17:23:56","up_fmt":"21 Agu 2023","up_short":"21 Agu","title":"Bokep Indo Ngentot Cici Ms Breewc Lagi Main Game Bokepsin Doodstream Doodsflix","t_esc":"Bokep Indo Ngentot Cici Ms Breewc Lagi Main Game Bokepsin Doodstream Doodsflix"},{"download_url":"https://myvidplay.com/d/1t7g0d06o9og","single_img":"https://thumbcdn.com/snaps/0imgaqv4ub0nlcrq.jpg","file_code":"1t7g0d06o9og","length":"00:10:55","views":"16671","vw_fmt":"16.7K","uploaded":"2023-08-21 17:23:55","up_fmt":"21 Agu 2023","up_short":"21 Agu","title":"Bokep Indo Msbreewc Cosplay Jadi Siswi Smp Chindo Bokepsin Com Bebasindo Dood","t_esc":"Bokep Indo Msbreewc Cosplay Jadi Siswi Smp Chindo Bokepsin Com Bebasindo Dood"},{"download_url":"https://myvidplay.com/d/v0lkauwy99rq","single_img":"https://thumbcdn.com/snaps/6ev2evz2soszxeay.jpg","file_code":"v0lkauwy99rq","length":"00:11:26","views":"20472","vw_fmt":"20.5K","uploaded":"2023-08-21 17:20:51","up_fmt":"21 Agu 2023","up_short":"21 Agu","title":"Ms Breewc Pulang Sekolah Eh Tiba Sange Update Staklam Doods Pro Pemersatu","t_esc":"Ms Breewc Pulang Sekolah Eh Tiba Sange Update Staklam Doods Pro Pemersatu"},{"download_url":"https://myvidplay.com/d/cj48dkv6xptp","single_img":"https://thumbcdn.com/snaps/wvccas8fksqahznf.jpg","file_code":"cj48dkv6xptp","length":"00:02:24","views":"28592","vw_fmt":"28.6K","uploaded":"2023-08-21 13:43:20","up_fmt":"21 Agu 2023","up_short":"21 Agu","title":"Bokep Indo Pelajar Smp Di Ewe Kakak Tiri Viral Bokepin Sotwe Lulustream","t_esc":"Bokep Indo Pelajar Smp Di Ewe Kakak Tiri Viral Bokepin Sotwe Lulustream"},{"download_url":"https://myvidplay.com/d/uuyts3vgnjhu","single_img":"https://thumbcdn.com/snaps/b24tghhl4ns9xxlg.jpg","file_code":"uuyts3vgnjhu","length":"00:05:02","views":"131725","vw_fmt":"131.7K","uploaded":"2023-08-21 13:43:20","up_fmt":"21 Agu 2023","up_short":"21 Agu","title":"Bokep Indo Pelajar Smp Dientot Kakak Jemput Sekolah Bokepsin Com Simontok Doodflix","t_esc":"Bokep Indo Pelajar Smp Dientot Kakak Jemput Sekolah Bokepsin Com Simontok Doodflix"},{"download_url":"https://myvidplay.com/d/uaif5beeav6a","single_img":"https://thumbcdn.com/snaps/8gkqes0e5lyf4qnb.jpg","file_code":"uaif5beeav6a","length":"00:19:48","views":"15151","vw_fmt":"15.2K","uploaded":"2023-08-21 13:43:20","up_fmt":"21 Agu 2023","up_short":"21 Agu","title":"Bokep Video Call Bugil Gadis Cantik Berkacamata Thailand Pelajar Smp Dood Stream","t_esc":"Bokep Video Call Bugil Gadis Cantik Berkacamata Thailand Pelajar Smp Dood Stream"},{"download_url":"https://myvidplay.com/d/sdbxcjltdibs","single_img":"https://thumbcdn.com/snaps/0kx26avnfz9zovht.jpg","file_code":"sdbxcjltdibs","length":"00:03:29","views":"4702","vw_fmt":"4.7K","uploaded":"2023-08-21 13:42:00","up_fmt":"21 Agu 2023","up_short":"21 Agu","title":"Part Anak Sma Nyewa Hotel Buat Praktek Tobrut Bokepin Indonesia Video Indo","t_esc":"Part Anak Sma Nyewa Hotel Buat Praktek Tobrut Bokepin Indonesia Video Indo"},{"download_url":"https://myvidplay.com/d/llmj29o3on65","single_img":"https://thumbcdn.com/snaps/9t8hb9scnjedzsch.jpg","file_code":"llmj29o3on65","length":"00:15:50","views":"11513","vw_fmt":"11.5K","uploaded":"2023-08-21 13:41:45","up_fmt":"21 Agu 2023","up_short":"21 Agu","title":"Culik Anak Sma Poophd Link Web Asupan Doods Pro Doodsflix","t_esc":"Culik Anak Sma Poophd Link Web Asupan Doods Pro Doodsflix"},{"download_url":"https://myvidplay.com/d/u86t8997oy4g","single_img":"https://thumbcdn.com/snaps/7exjspuvpsor36rj.jpg","file_code":"u86t8997oy4g","length":"00:19:29","views":"1717","vw_fmt":"1.7K","uploaded":"2023-08-21 13:40:16","up_fmt":"21 Agu 2023","up_short":"21 Agu","title":"Anak Sma Cantik Kehilangan Perawan Sama Om Update Website Link Web Dood","t_esc":"Anak Sma Cantik Kehilangan Perawan Sama Om Update Website Link Web Dood"},{"download_url":"https://myvidplay.com/d/00vwjwnz09ey","single_img":"https://thumbcdn.com/snaps/v92u9adri61kw66e.jpg","file_code":"00vwjwnz09ey","length":"00:13:27","views":"3865","vw_fmt":"3.9K","uploaded":"2023-08-21 13:39:59","up_fmt":"21 Agu 2023","up_short":"21 Agu","title":"Sekandal Anak Sma Nyepong Nya Masih Muntah Doodsflix Doodflix Yakwad Memeksiana Live","t_esc":"Sekandal Anak Sma Nyepong Nya Masih Muntah Doodsflix Doodflix Yakwad Memeksiana Live"},{"download_url":"https://myvidplay.com/d/0vdf6jwt6dbe","single_img":"https://thumbcdn.com/snaps/8befp98n8lilpw1i.jpg","file_code":"0vdf6jwt6dbe","length":"00:04:43","views":"30152","vw_fmt":"30.2K","uploaded":"2023-08-21 13:39:56","up_fmt":"21 Agu 2023","up_short":"21 Agu","title":"Kumpulan Vidio Bokep Rare Terbaru Yang Lagi Viral Dood Stream","t_esc":"Kumpulan Vidio Bokep Rare Terbaru Yang Lagi Viral Dood Stream"},{"download_url":"https://myvidplay.com/d/w3xag7vsmg50","single_img":"https://thumbcdn.com/snaps/4hc0pkmzez17xms0.jpg","file_code":"w3xag7vsmg50","length":"00:00:26","views":"676","vw_fmt":"676","uploaded":"2023-08-21 13:39:30","up_fmt":"21 Agu 2023","up_short":"21 Agu","title":"Viral Damayanti Anak Sma Jaksel Terupdate Update Bokep Full Album Telegram","t_esc":"Viral Damayanti Anak Sma Jaksel Terupdate Update Bokep Full Album Telegram"},{"download_url":"https://myvidplay.com/d/ajbt6tzhplmk","single_img":"https://thumbcdn.com/snaps/f8rz231ugblgrsf4.jpg","file_code":"ajbt6tzhplmk","length":"00:00:24","views":"3987","vw_fmt":"4.0K","uploaded":"2023-08-21 13:39:22","up_fmt":"21 Agu 2023","up_short":"21 Agu","title":"Viral Damayanti Anak Sma Jaksel Pejuang Lendir Tiktok Toketbagus Popstream Tele","t_esc":"Viral Damayanti Anak Sma Jaksel Pejuang Lendir Tiktok Toketbagus Popstream Tele"},{"download_url":"https://myvidplay.com/d/wrzr32jcqqfa","single_img":"https://thumbcdn.com/snaps/ljqob0bq4k5enqsc.jpg","file_code":"wrzr32jcqqfa","length":"00:11:20","views":"11903","vw_fmt":"11.9K","uploaded":"2023-08-21 13:39:15","up_fmt":"21 Agu 2023","up_short":"21 Agu","title":"Stw Main Di Kosan Asupan Indo Downloader Terabox Doodflix","t_esc":"Stw Main Di Kosan Asupan Indo Downloader Terabox Doodflix"},{"download_url":"https://myvidplay.com/d/t3s7ka8js70m","single_img":"https://thumbcdn.com/snaps/4axdkx4i0ktq86yi.jpg","file_code":"t3s7ka8js70m","length":"00:01:28","views":"868","vw_fmt":"868","uploaded":"2023-08-21 13:39:13","up_fmt":"21 Agu 2023","up_short":"21 Agu","title":"Cosplay Anak Sma Ngewe Dood Stream Lulustream Indonesia Bokep Tiktok","t_esc":"Cosplay Anak Sma Ngewe Dood Stream Lulustream Indonesia Bokep Tiktok"},{"download_url":"https://myvidplay.com/d/k6p22iqwxy9n","single_img":"https://thumbcdn.com/snaps/9e9de96l8fcjccz2.jpg","file_code":"k6p22iqwxy9n","length":"00:01:05","views":"3334","vw_fmt":"3.3K","uploaded":"2023-08-21 13:38:53","up_fmt":"21 Agu 2023","up_short":"21 Agu","title":"Kenikmatan Anak Sma Asupan Doodflix Bokep Lokal Terabox","t_esc":"Kenikmatan Anak Sma Asupan Doodflix Bokep Lokal Terabox"},{"download_url":"https://myvidplay.com/d/nl9s4ly7vytf","single_img":"https://thumbcdn.com/snaps/i0vy5ba5btf02lcc.jpg","file_code":"nl9s4ly7vytf","length":"00:02:20","views":"1216","vw_fmt":"1.2K","uploaded":"2023-08-21 13:38:43","up_fmt":"21 Agu 2023","up_short":"21 Agu","title":"Nostalgia Skandal Anak Sma Update Videos Sotwe Simontok Staklam","t_esc":"Nostalgia Skandal Anak Sma Update Videos Sotwe Simontok Staklam"},{"download_url":"https://myvidplay.com/d/qc0a6wzt5r2o","single_img":"https://thumbcdn.com/snaps/cbjqpc6cendehscz.jpg","file_code":"qc0a6wzt5r2o","length":"00:15:50","views":"8977","vw_fmt":"9.0K","uploaded":"2023-08-21 13:38:30","up_fmt":"21 Agu 2023","up_short":"21 Agu","title":"Freya Anak Sma Bokep Dood Bochiel Doods Pro Video Viral Ngentot","t_esc":"Freya Anak Sma Bokep Dood Bochiel Doods Pro Video Viral Ngentot"},{"download_url":"https://myvidplay.com/d/76ncxgtjofz8","single_img":"https://thumbcdn.com/snaps/2x7ejgrm7hwndpll.jpg","file_code":"76ncxgtjofz8","length":"00:03:16","views":"1140","vw_fmt":"1.1K","uploaded":"2023-08-21 13:38:00","up_fmt":"21 Agu 2023","up_short":"21 Agu","title":"Bokep Ngewe Anak Sma Hijab Di Hotel Dood Stream Simintok Indonesia Viral","t_esc":"Bokep Ngewe Anak Sma Hijab Di Hotel Dood Stream Simintok Indonesia Viral"},{"download_url":"https://myvidplay.com/d/fvmqjc07qa54","single_img":"https://thumbcdn.com/snaps/glf54r5vd441pfu5.jpg","file_code":"fvmqjc07qa54","length":"00:10:51","views":"2722","vw_fmt":"2.7K","uploaded":"2023-08-21 13:37:57","up_fmt":"21 Agu 2023","up_short":"21 Agu","title":"Cosplay Anak Sma Binal Prank Kang Ojol Cilbo Staklam Bokep Dood Videos","t_esc":"Cosplay Anak Sma Binal Prank Kang Ojol Cilbo Staklam Bokep Dood Videos"},{"download_url":"https://myvidplay.com/d/tosfl9z52jn3","single_img":"https://thumbcdn.com/snaps/isdeqmeh4ei8q4sb.jpg","file_code":"tosfl9z52jn3","length":"00:15:18","views":"190159","vw_fmt":"190.2K","uploaded":"2023-08-21 13:36:36","up_fmt":"21 Agu 2023","up_short":"21 Agu","title":"Sma Acha Anak Motor Ngw Ful Album Bokep Video Terupdate Dodstream Pejuang","t_esc":"Sma Acha Anak Motor Ngw Ful Album Bokep Video Terupdate Dodstream Pejuang"},{"download_url":"https://myvidplay.com/d/8upp01jx6pl2","single_img":"https://thumbcdn.com/snaps/hz93afzvu65ry3rn.jpg","file_code":"8upp01jx6pl2","length":"00:06:54","views":"28106","vw_fmt":"28.1K","uploaded":"2023-08-21 13:36:32","up_fmt":"21 Agu 2023","up_short":"21 Agu","title":"Anak Sma Rela Di Setubuhi Demi Uang Jajan Asupan Cilbo Toketbagus Memeksiana","t_esc":"Anak Sma Rela Di Setubuhi Demi Uang Jajan Asupan Cilbo Toketbagus Memeksiana"}],"results_total":"26531","results":200}}