{"msg":"OK","server_time":"2026-04-11 05:00:08","status":200,"result":{"total_pages":900,"files":[{"download_url":"https://playmogo.com/d/rxno0w9tzqt0","si":"https://ticdn.net/snaps/6h83lj62z3p1ve5u.jpg","f":"rxno0w9tzqt0","ln":442,"vw":"92","vw_fmt":"92","up":"2026-03-10 10:45:06","up_fmt":"10 Mar 2026","kt":"Video Telegram","as":"doodstream","up_short":"10 Mar","t":"Pijat Seks Bogor Kota Twitter Videy Link Telegram Popstream","t_esc":"Pijat Seks Bogor Kota Twitter Videy Link Telegram Popstream","seo_url":"pijat-seks-bogor-kota-twitter-videy-link-telegram-popstream"},{"download_url":"https://playmogo.com/d/uu5y40mcqitc","si":"https://ticdn.net/snaps/uxofeo282ezeuuf1.jpg","f":"uu5y40mcqitc","ln":105,"vw":"53","vw_fmt":"53","up":"2026-03-10 10:45:06","up_fmt":"10 Mar 2026","kt":"Video Enak","as":"doodstream","up_short":"10 Mar","t":"Enak Ngewe Open Bo Toge Full Album Video Yandex Bokepindo","t_esc":"Enak Ngewe Open Bo Toge Full Album Video Yandex Bokepindo","seo_url":"enak-ngewe-open-bo-toge-full-album-video-yandex-bokepindo"},{"download_url":"https://playmogo.com/d/07cf4nlrahwr","si":"https://ticdn.net/snaps/km68wa93tu5m4va1.jpg","f":"07cf4nlrahwr","ln":2603,"vw":"56","vw_fmt":"56","up":"2026-03-10 10:45:06","up_fmt":"10 Mar 2026","kt":"Video Ayang","as":"doodstream","up_short":"10 Mar","t":"Ayang Prank Ojol Video Wiki Staklam Xpanas","t_esc":"Ayang Prank Ojol Video Wiki Staklam Xpanas","seo_url":"ayang-prank-ojol-video-wiki-staklam-xpanas"},{"download_url":"https://playmogo.com/d/7n0v4nuby34r","si":"https://ticdn.net/snaps/skxl40ynwy7kui75.jpg","f":"7n0v4nuby34r","ln":1675,"vw":"198","vw_fmt":"198","up":"2026-03-10 10:45:06","up_fmt":"10 Mar 2026","kt":"Video Lulustream","as":"doodstream","up_short":"10 Mar","t":"Awalnya Malu Akhirnya Euw Gasin Semua Gaya Bokepsatset Video Viral Lulustream","t_esc":"Awalnya Malu Akhirnya Euw Gasin Semua Gaya Bokepsatset Video Viral Lulustream","seo_url":"awalnya-malu-akhirnya-euw-gasin-gaya-bokepsatset-video-viral-lulustream"},{"download_url":"https://playmogo.com/d/cuy9xqkqhbm6","si":"https://ticdn.net/snaps/yyj5ova83mmqpql6.jpg","f":"cuy9xqkqhbm6","ln":315,"vw":"197","vw_fmt":"197","up":"2026-03-10 10:45:06","up_fmt":"10 Mar 2026","kt":"Video Pulang","as":"doodstream","up_short":"10 Mar","t":"Pulang Kuliah Malah Langsung Ngentod Masih Berseragam Video Bokep Link Asupan Pemersatu","t_esc":"Pulang Kuliah Malah Langsung Ngentod Masih Berseragam Video Bokep Link Asupan Pemersatu","seo_url":"pulang-kuliah-malah-langsung-ngentod-berseragam-video-bokep-link-asupan-pemersatu"},{"download_url":"https://playmogo.com/d/cyqs4dlqngf8","si":"https://ticdn.net/snaps/lax70le0ex4v7nt6.jpg","f":"cyqs4dlqngf8","ln":449,"vw":"228","vw_fmt":"228","up":"2026-03-10 10:45:06","up_fmt":"10 Mar 2026","kt":"Video Teman","as":"doodstream","up_short":"10 Mar","t":"Teman Tapi Ngentot Popstream Xpanas Full Album","t_esc":"Teman Tapi Ngentot Popstream Xpanas Full Album","seo_url":"teman-ngentot-popstream-xpanas-full-album"},{"download_url":"https://playmogo.com/d/8g7pri2rckwf","si":"https://ticdn.net/snaps/ok2vvckrfw2vkzcn.jpg","f":"8g7pri2rckwf","ln":643,"vw":"136","vw_fmt":"136","up":"2026-03-10 10:45:06","up_fmt":"10 Mar 2026","kt":"Video Telegram","as":"doodstream","up_short":"10 Mar","t":"Cindo Gangbang Pejuang Lendir Bokepind Videy Link Telegram","t_esc":"Cindo Gangbang Pejuang Lendir Bokepind Videy Link Telegram","seo_url":"cindo-gangbang-pejuang-lendir-bokepind-videy-link-telegram"},{"download_url":"https://playmogo.com/d/jfia7tgblefr","si":"https://ticdn.net/snaps/arrjwif9nne4h5kr.jpg","f":"jfia7tgblefr","ln":85,"vw":"39","vw_fmt":"39","up":"2026-03-10 10:45:06","up_fmt":"10 Mar 2026","kt":"Video Doodstream","as":"doodstream","up_short":"10 Mar","t":"Abg Ngewe Sama Pacar Dood Stream Terupdate Video Yandex Doodstream","t_esc":"Abg Ngewe Sama Pacar Dood Stream Terupdate Video Yandex Doodstream","seo_url":"abg-ngewe-sama-pacar-dood-stream-terupdate-video-yandex-doodstream"},{"download_url":"https://playmogo.com/d/nuxmkv78px0d","si":"https://ticdn.net/snaps/96nzrs8dqlmd1fhi.jpg","f":"nuxmkv78px0d","ln":240,"vw":"96","vw_fmt":"96","up":"2026-03-10 10:45:06","up_fmt":"10 Mar 2026","kt":"Video Memeksiana","as":"doodstream","up_short":"10 Mar","t":"Ngentot Ayang Crot Dalam Memek Dood Stream Bokepindo Bokep Memeksiana","t_esc":"Ngentot Ayang Crot Dalam Memek Dood Stream Bokepindo Bokep Memeksiana","seo_url":"ngentot-ayang-crot-memek-dood-stream-bokepindo-bokep-memeksiana"},{"download_url":"https://playmogo.com/d/bk83gmh2y4by","si":"https://ticdn.net/snaps/alkl44st6jhnewvs.jpg","f":"bk83gmh2y4by","ln":200,"vw":"91","vw_fmt":"91","up":"2026-03-10 10:45:06","up_fmt":"10 Mar 2026","kt":"Video Bokepsatset","as":"doodstream","up_short":"10 Mar","t":"Alikka Sma Bekasi Viral Xpanas Doodflix Bokepsatset","t_esc":"Alikka Sma Bekasi Viral Xpanas Doodflix Bokepsatset","seo_url":"alikka-sma-bekasi-viral-xpanas-doodflix-bokepsatset"},{"download_url":"https://playmogo.com/d/wi8nwgfu2owx","si":"https://ticdn.net/snaps/u5apo006oxtr6kag.jpg","f":"wi8nwgfu2owx","ln":470,"vw":"24","vw_fmt":"24","up":"2026-03-10 10:45:06","up_fmt":"10 Mar 2026","kt":"Video Memeksiana","as":"doodstream","up_short":"10 Mar","t":"Jeenzen Produced For Stream Pejuang Lendir Memeksiana Asupan Viral","t_esc":"Jeenzen Produced For Stream Pejuang Lendir Memeksiana Asupan Viral","seo_url":"jeenzen-produced-for-stream-pejuang-lendir-memeksiana-asupan-viral"},{"download_url":"https://playmogo.com/d/jlgvazdnvfl3","si":"https://ticdn.net/snaps/x2ucivi3k84wa1ym.jpg","f":"jlgvazdnvfl3","ln":110,"vw":"189","vw_fmt":"189","up":"2026-03-10 10:45:06","up_fmt":"10 Mar 2026","kt":"Video Skandal","as":"doodstream","up_short":"10 Mar","t":"Skandal Siswi Sma Toket Mulus Dood Stream Popstream Video Yandex Memeksiana","t_esc":"Skandal Siswi Sma Toket Mulus Dood Stream Popstream Video Yandex Memeksiana","seo_url":"skandal-siswi-sma-toket-mulus-dood-stream-popstream-video-yandex-memeksiana"},{"download_url":"https://playmogo.com/d/2dfepg7crxiq","si":"https://ticdn.net/snaps/m6htdappw4sxu7vu.jpg","f":"2dfepg7crxiq","ln":120,"vw":"117","vw_fmt":"117","up":"2026-03-10 10:45:06","up_fmt":"10 Mar 2026","kt":"Video Tobrut","as":"doodstream","up_short":"10 Mar","t":"Binor Tobrut Kesakitan Udah Croot Di Genjot Terus G A Update Bebasindo Bokepind","t_esc":"Binor Tobrut Kesakitan Udah Croot Di Genjot Terus G A Update Bebasindo Bokepind","seo_url":"binor-tobrut-kesakitan-udah-croot-genjot-terus-g-a-update-bebasindo-bokepind"},{"download_url":"https://playmogo.com/d/fnr52cs2on51","si":"https://ticdn.net/snaps/lii25j4zoqu6rs7h.jpg","f":"fnr52cs2on51","ln":105,"vw":"40","vw_fmt":"40","up":"2026-03-10 10:45:06","up_fmt":"10 Mar 2026","kt":"Video Doodstream","as":"doodstream","up_short":"10 Mar","t":"Princess Mecardo Doodstream Popstream Dood Tele Doods Pro","t_esc":"Princess Mecardo Doodstream Popstream Dood Tele Doods Pro","seo_url":"princess-mecardo-doodstream-popstream-dood-tele-doods-pro"},{"download_url":"https://playmogo.com/d/1k676amt73so","si":"https://ticdn.net/snaps/lysqerlo6vs9momz.jpg","f":"1k676amt73so","ln":99,"vw":"35","vw_fmt":"35","up":"2026-03-10 10:45:06","up_fmt":"10 Mar 2026","kt":"Video Telegram","as":"doodstream","up_short":"10 Mar","t":"Kang Galon Dood Stream Telegram Doodstreem Website","t_esc":"Kang Galon Dood Stream Telegram Doodstreem Website","seo_url":"kang-galon-dood-stream-telegram-doodstreem-website"},{"download_url":"https://playmogo.com/d/gznug7ljcr60","si":"https://ticdn.net/snaps/ryw3gxezn96tv5y6.jpg","f":"gznug7ljcr60","ln":232,"vw":"0","vw_fmt":"0","up":"2026-03-10 10:45:06","up_fmt":"10 Mar 2026","kt":"Video Terabox","as":"doodstream","up_short":"10 Mar","t":"Anisa Rahmawati Full Stream Videos Terabox Doodstream","t_esc":"Anisa Rahmawati Full Stream Videos Terabox Doodstream","seo_url":"anisa-rahmawati-full-stream-videos-terabox-doodstream"},{"download_url":"https://playmogo.com/d/qqfhmy4cg3nz","si":"https://ticdn.net/snaps/vmc4xzqs017y3of2.jpg","f":"qqfhmy4cg3nz","ln":118,"vw":"100","vw_fmt":"100","up":"2026-03-10 10:45:06","up_fmt":"10 Mar 2026","kt":"Video Ngetot","as":"doodstream","up_short":"10 Mar","t":"Ngetot Sblh Teman Lagi Tidur Dood Stream Links Tele Xpanas Viral","t_esc":"Ngetot Sblh Teman Lagi Tidur Dood Stream Links Tele Xpanas Viral","seo_url":"ngetot-sblh-teman-lagi-tidur-dood-stream-links-tele-xpanas-viral"},{"download_url":"https://playmogo.com/d/qzyu7zmkddw5","si":"https://ticdn.net/snaps/29nqaesywh05mo9c.jpg","f":"qzyu7zmkddw5","ln":781,"vw":"56","vw_fmt":"56","up":"2026-03-10 10:45:06","up_fmt":"10 Mar 2026","kt":"Video Skandal","as":"doodstream","up_short":"10 Mar","t":"Abg Zaman Sekaang Ud Stream Pekoblive Video Sotwe Skandal Mesum","t_esc":"Abg Zaman Sekaang Ud Stream Pekoblive Video Sotwe Skandal Mesum","seo_url":"abg-zaman-sekaang-ud-stream-pekoblive-video-sotwe-skandal-mesum"},{"download_url":"https://playmogo.com/d/zudn3zvrkn8d","si":"https://ticdn.net/snaps/4nfyro72usjaav89.jpg","f":"zudn3zvrkn8d","ln":535,"vw":"79","vw_fmt":"79","up":"2026-03-10 10:44:57","up_fmt":"10 Mar 2026","kt":"Video Pacar","as":"doodstream","up_short":"10 Mar","t":"Pacar Orang Di Pake Stream Update Bokepindo Asupan Viral","t_esc":"Pacar Orang Di Pake Stream Update Bokepindo Asupan Viral","seo_url":"pacar-orang-pake-stream-update-bokepindo-asupan-viral"},{"download_url":"https://playmogo.com/d/jn58hcumiarg","si":"https://ticdn.net/snaps/m4lqfo1lyr1jck3n.jpg","f":"jn58hcumiarg","ln":1383,"vw":"155","vw_fmt":"155","up":"2026-03-10 10:44:57","up_fmt":"10 Mar 2026","kt":"Video Skandal","as":"doodstream","up_short":"10 Mar","t":"Nabila Foreplay Telegram Links Tele Skandal Mesum","t_esc":"Nabila Foreplay Telegram Links Tele Skandal Mesum","seo_url":"nabila-foreplay-telegram-links-tele-skandal-mesum"},{"download_url":"https://playmogo.com/d/9my8smmse44w","si":"https://ticdn.net/snaps/6ncshksy07bj8gps.jpg","f":"9my8smmse44w","ln":367,"vw":"537","vw_fmt":"537","up":"2026-03-10 10:44:57","up_fmt":"10 Mar 2026","kt":"Video Bokep","as":"doodstream","up_short":"10 Mar","t":"Bokep Ngewe Pacar Dikost Full Percakapan Xbokep Fb Video Viral Xpanas Popstream","t_esc":"Bokep Ngewe Pacar Dikost Full Percakapan Xbokep Fb Video Viral Xpanas Popstream","seo_url":"bokep-ngewe-pacar-dikost-full-percakapan-xbokep-fb-video-viral-xpanas-popstream"},{"download_url":"https://playmogo.com/d/q89d9vsv32ek","si":"https://ticdn.net/snaps/ojmkmokbf8kvhb6y.jpg","f":"q89d9vsv32ek","ln":449,"vw":"124","vw_fmt":"124","up":"2026-03-10 10:44:57","up_fmt":"10 Mar 2026","kt":"Video Hijab","as":"doodstream","up_short":"10 Mar","t":"Hijab Pink Memek Sempit Kesakitan Dood Stream Yakwad Update Doodflix","t_esc":"Hijab Pink Memek Sempit Kesakitan Dood Stream Yakwad Update Doodflix","seo_url":"hijab-pink-memek-sempit-kesakitan-dood-stream-yakwad-update-doodflix"},{"download_url":"https://playmogo.com/d/bvgt7pr7v4x4","si":"https://ticdn.net/snaps/xt3qntg62665wdq4.jpg","f":"bvgt7pr7v4x4","ln":127,"vw":"144","vw_fmt":"144","up":"2026-03-10 10:44:57","up_fmt":"10 Mar 2026","kt":"Video Guru","as":"doodstream","up_short":"10 Mar","t":"Guru Pns Tiktok Video Yandex Toketbagus","t_esc":"Guru Pns Tiktok Video Yandex Toketbagus","seo_url":"guru-pns-tiktok-video-yandex-toketbagus"},{"download_url":"https://playmogo.com/d/sp2xyt1gb7bo","si":"https://ticdn.net/snaps/z90i5b6x5f1sotbc.jpg","f":"sp2xyt1gb7bo","ln":81,"vw":"34","vw_fmt":"34","up":"2026-03-10 10:44:57","up_fmt":"10 Mar 2026","kt":"Video Viral","as":"doodstream","up_short":"10 Mar","t":"Viral Anak Perguruan Pencak Silat Ngentot Lagi Pejuang Lendir Yakwad","t_esc":"Viral Anak Perguruan Pencak Silat Ngentot Lagi Pejuang Lendir Yakwad","seo_url":"viral-anak-perguruan-pencak-silat-ngentot-lagi-pejuang-lendir-yakwad"},{"download_url":"https://playmogo.com/d/3y0bj6nc5l8z","si":"https://ticdn.net/snaps/kex1xq36gnw74f0h.jpg","f":"3y0bj6nc5l8z","ln":109,"vw":"108","vw_fmt":"108","up":"2026-03-10 10:44:57","up_fmt":"10 Mar 2026","kt":"Video Lulustream","as":"doodstream","up_short":"10 Mar","t":"Skandal Bos Dan Karyawan Dood Stream Bokep Video Bokepindo Lulustream","t_esc":"Skandal Bos Dan Karyawan Dood Stream Bokep Video Bokepindo Lulustream","seo_url":"skandal-bos-karyawan-dood-stream-bokep-video-bokepindo-lulustream"},{"download_url":"https://playmogo.com/d/bg3jh3watb05","si":"https://ticdn.net/snaps/a4tranczl7ze1c6q.jpg","f":"bg3jh3watb05","ln":1222,"vw":"370","vw_fmt":"370","up":"2026-03-10 10:44:53","up_fmt":"10 Mar 2026","kt":"Video Hijab","as":"doodstream","up_short":"10 Mar","t":"Hijab Viral Update Twitter Tiktok","t_esc":"Hijab Viral Update Twitter Tiktok","seo_url":"hijab-viral-update-twitter-tiktok"},{"download_url":"https://playmogo.com/d/x5odbpwqp925","si":"https://ticdn.net/snaps/4720zcgrw3w8unkp.jpg","f":"x5odbpwqp925","ln":575,"vw":"54","vw_fmt":"54","up":"2026-03-10 10:44:53","up_fmt":"10 Mar 2026","kt":"Video Arizarafifa","as":"doodstream","up_short":"10 Mar","t":"Arizarafifa Dood Stream Streaming Bokepin Bokepsin","t_esc":"Arizarafifa Dood Stream Streaming Bokepin Bokepsin","seo_url":"arizarafifa-dood-stream-streaming-bokepin-bokepsin"},{"download_url":"https://playmogo.com/d/kto3t113xqqa","si":"https://ticdn.net/snaps/u5b73vjd7cx4rt9c.jpg","f":"kto3t113xqqa","ln":119,"vw":"54","vw_fmt":"54","up":"2026-03-10 10:44:53","up_fmt":"10 Mar 2026","kt":"Video Nayla","as":"doodstream","up_short":"10 Mar","t":"Nayla Dood Stream Viral Videos Pejuang Lendir","t_esc":"Nayla Dood Stream Viral Videos Pejuang Lendir","seo_url":"nayla-dood-stream-viral-videos-pejuang-lendir"},{"download_url":"https://playmogo.com/d/2ajw9p0rpdbs","si":"https://ticdn.net/snaps/v5g8fvd4xuz3c2s4.jpg","f":"2ajw9p0rpdbs","ln":382,"vw":"172","vw_fmt":"172","up":"2026-03-10 10:44:53","up_fmt":"10 Mar 2026","kt":"Video Doodstream","as":"doodstream","up_short":"10 Mar","t":"Ruang Tamu Dood Str Stream Doodstream Yakwad Poophd","t_esc":"Ruang Tamu Dood Str Stream Doodstream Yakwad Poophd","seo_url":"ruang-tamu-dood-str-stream-doodstream-yakwad-poophd"},{"download_url":"https://playmogo.com/d/zpwe0pqd98ao","si":"https://ticdn.net/snaps/z4ukd2zvz43lbpoq.jpg","f":"zpwe0pqd98ao","ln":95,"vw":"174","vw_fmt":"174","up":"2026-03-10 10:44:53","up_fmt":"10 Mar 2026","kt":"Video Lulustream","as":"doodstream","up_short":"10 Mar","t":"Panya New Tele Linkviralgoy Lulustream Xpanas Bokepindo","t_esc":"Panya New Tele Linkviralgoy Lulustream Xpanas Bokepindo","seo_url":"panya-new-tele-linkviralgoy-lulustream-xpanas-bokepindo"}],"results_total":"26986","results":30}}