{"msg":"OK","server_time":"2026-04-05 05:18:25","status":200,"result":{"total_pages":882,"files":[{"download_url":"https://playmogo.com/d/3pba0qjqoyln","si":"https://thumbcdn.com/snaps/5zhw3cd7qjiqmg3a.jpg","f":"3pba0qjqoyln","ln":256,"vw":"1104","vw_fmt":"1.1K","up":"2023-11-24 15:16:15","up_fmt":"24 Nov 2023","kt":"Video Tante","as":"doodstream","up_short":"24 Nov","t":"Si Tante Suka Jilat Video Yandex Bokepind Popstream","t_esc":"Si Tante Suka Jilat Video Yandex Bokepind Popstream","seo_url":"tante-suka-jilat-video-yandex-bokepind-popstream"},{"download_url":"https://playmogo.com/d/l5kcoixl77rm","si":"https://thumbcdn.com/snaps/gaoukcu8akjo6uup.jpg","f":"l5kcoixl77rm","ln":989,"vw":"6304","vw_fmt":"6.3K","up":"2023-11-24 15:16:13","up_fmt":"24 Nov 2023","kt":"Video Stw","as":"doodstream","up_short":"24 Nov","t":"Konten Video Stw Stream Dood Yakwad Staklam Link Pemersatu","t_esc":"Konten Video Stw Stream Dood Yakwad Staklam Link Pemersatu","seo_url":"konten-video-stw-stream-dood-yakwad-staklam-link-pemersatu"},{"download_url":"https://playmogo.com/d/oczpvka9294d","si":"https://thumbcdn.com/snaps/vvzo5x6xo9scy17a.jpg","f":"oczpvka9294d","ln":1064,"vw":"6185","vw_fmt":"6.2K","up":"2023-11-24 15:16:12","up_fmt":"24 Nov 2023","kt":"Video Bikin","as":"doodstream","up_short":"24 Nov","t":"Bikin Pascol Mango Ngaceng Gea Baik N Cntik Jilat Tt Bokepind Lagi Viral Video Wiki","t_esc":"Bikin Pascol Mango Ngaceng Gea Baik N Cntik Jilat Tt Bokepind Lagi Viral Video Wiki","seo_url":"bikin-pascol-mango-ngaceng-gea-baik-n-cntik-jilat-tt-bokepind-lagi-viral-video-wiki"},{"download_url":"https://playmogo.com/d/i9sizbzf8297","si":"https://thumbcdn.com/snaps/e7xvxxvizue7igp9.jpg","f":"i9sizbzf8297","ln":720,"vw":"1399","vw_fmt":"1.4K","up":"2023-11-24 15:16:11","up_fmt":"24 Nov 2023","kt":"Video Lulustream","as":"doodstream","up_short":"24 Nov","t":"Bokep Cewek Tobrut Jilat Uting Mantap Emang Gak Ada Lawan Vibokep Video Sotwe Lulustream Asupan Viral","t_esc":"Bokep Cewek Tobrut Jilat Uting Mantap Emang Gak Ada Lawan Vibokep Video Sotwe Lulustream Asupan Viral","seo_url":"bokep-cewek-tobrut-jilat-uting-mantap-emang-gak-lawan-vibokep-video-sotwe-lulustream-asupan-viral"},{"download_url":"https://playmogo.com/d/tqpiq22uw4u5","si":"https://thumbcdn.com/snaps/9c4v4r5fwd2njeg8.jpg","f":"tqpiq22uw4u5","ln":15,"vw":"2097","vw_fmt":"2.1K","up":"2023-11-24 15:16:11","up_fmt":"24 Nov 2023","kt":"Video Jilbab","as":"doodstream","up_short":"24 Nov","t":"Jilbab Hitam Baju Biru Jilat Kontol Dood Stream Bokepsatset Bokepin Popstream","t_esc":"Jilbab Hitam Baju Biru Jilat Kontol Dood Stream Bokepsatset Bokepin Popstream","seo_url":"jilbab-hitam-baju-biru-jilat-kontol-dood-stream-bokepsatset-bokepin-popstream"},{"download_url":"https://playmogo.com/d/zyu6xdgmbmsx","si":"https://thumbcdn.com/snaps/yvkvbl5qtjn1672m.jpg","f":"zyu6xdgmbmsx","ln":671,"vw":"5440","vw_fmt":"5.4K","up":"2023-11-24 15:16:09","up_fmt":"24 Nov 2023","kt":"Video Msbreewc","as":"doodstream","up_short":"24 Nov","t":"Cici Nyepong Rimming Jilat Peler Crotin Doi Msbreewc Avtub Update Video Yandex Full Album","t_esc":"Cici Nyepong Rimming Jilat Peler Crotin Doi Msbreewc Avtub Update Video Yandex Full Album","seo_url":"cici-nyepong-rimming-jilat-peler-crotin-doi-msbreewc-avtub-update-video-yandex-full-album"},{"download_url":"https://playmogo.com/d/efu78byny8ih","si":"https://thumbcdn.com/snaps/fkqkp75egqn1n1ih.jpg","f":"efu78byny8ih","ln":226,"vw":"665","vw_fmt":"665","up":"2023-11-24 15:16:09","up_fmt":"24 Nov 2023","kt":"Video Bokepsatset","as":"doodstream","up_short":"24 Nov","t":"Tante Jilat Tt Video Sotwe Bokepsatset Bokep","t_esc":"Tante Jilat Tt Video Sotwe Bokepsatset Bokep","seo_url":"tante-jilat-tt-video-sotwe-bokepsatset-bokep"},{"download_url":"https://playmogo.com/d/33fv9m7yyar3","si":"https://thumbcdn.com/snaps/900il3swktfxhsav.jpg","f":"33fv9m7yyar3","ln":3879,"vw":"1267","vw_fmt":"1.3K","up":"2023-11-24 15:15:58","up_fmt":"24 Nov 2023","kt":"Video Telegram","as":"doodstream","up_short":"24 Nov","t":"Moa Cantik Toket Gede Buat Bacol Bebasindo Video Bokep Telegram","t_esc":"Moa Cantik Toket Gede Buat Bacol Bebasindo Video Bokep Telegram","seo_url":"moa-cantik-toket-gede-buat-bacol-bebasindo-video-bokep-telegram"},{"download_url":"https://playmogo.com/d/g4wmtejkxfrc","si":"https://thumbcdn.com/snaps/6zh3gr9mieoarf1i.jpg","f":"g4wmtejkxfrc","ln":168,"vw":"5199","vw_fmt":"5.2K","up":"2023-11-24 15:15:01","up_fmt":"24 Nov 2023","kt":"Video Doodstream","as":"doodstream","up_short":"24 Nov","t":"Uting Bocah Gede Doodsflix Doodstream Pejuang Lendir","t_esc":"Uting Bocah Gede Doodsflix Doodstream Pejuang Lendir","seo_url":"uting-bocah-gede-doodsflix-doodstream-pejuang-lendir"},{"download_url":"https://playmogo.com/d/e48ia30ds1p9","si":"https://thumbcdn.com/snaps/fmauwywyjuwuu40e.jpg","f":"e48ia30ds1p9","ln":81,"vw":"2007","vw_fmt":"2.0K","up":"2023-11-24 15:15:00","up_fmt":"24 Nov 2023","kt":"Video Telegram","as":"doodstream","up_short":"24 Nov","t":"Pap Buat Pacar Tete Gede Pejuang Lendir Videy Link Telegram Video Wiki","t_esc":"Pap Buat Pacar Tete Gede Pejuang Lendir Videy Link Telegram Video Wiki","seo_url":"pap-buat-pacar-tete-gede-pejuang-lendir-videy-link-telegram-video-wiki"},{"download_url":"https://playmogo.com/d/s1aff50d4v93","si":"https://thumbcdn.com/snaps/lxn4zqrgz9hbkvdf.jpg","f":"s1aff50d4v93","ln":84,"vw":"1145","vw_fmt":"1.1K","up":"2023-11-24 15:15:00","up_fmt":"24 Nov 2023","kt":"Video Pakai","as":"doodstream","up_short":"24 Nov","t":"Pakai Terong Gede Doodflix Pekoblive Video Yandex","t_esc":"Pakai Terong Gede Doodflix Pekoblive Video Yandex","seo_url":"pakai-terong-gede-doodflix-pekoblive-video-yandex"},{"download_url":"https://playmogo.com/d/spdncytrhxsj","si":"https://thumbcdn.com/snaps/mpharsofp1pdyee3.jpg","f":"spdncytrhxsj","ln":1124,"vw":"2243","vw_fmt":"2.2K","up":"2023-11-24 15:14:58","up_fmt":"24 Nov 2023","kt":"Video Doodstream","as":"doodstream","up_short":"24 Nov","t":"Mbak Pijat Sange Liat Kontol Gede Bokep Dood Doodstream Tiktok","t_esc":"Mbak Pijat Sange Liat Kontol Gede Bokep Dood Doodstream Tiktok","seo_url":"mbak-pijat-sange-liat-kontol-gede-bokep-dood-doodstream-tiktok"},{"download_url":"https://playmogo.com/d/4ho5kjpf4co4","si":"https://thumbcdn.com/snaps/bm699pqr69rworb3.jpg","f":"4ho5kjpf4co4","ln":958,"vw":"1866","vw_fmt":"1.9K","up":"2023-11-24 15:14:55","up_fmt":"24 Nov 2023","kt":"Video Gabby","as":"doodstream","up_short":"24 Nov","t":"Gabby Live We Sama Suami Orang Knt L Gede Kesuk Lagi Viral Bokep Dood Tele","t_esc":"Gabby Live We Sama Suami Orang Knt L Gede Kesuk Lagi Viral Bokep Dood Tele","seo_url":"gabby-live-we-sama-suami-orang-knt-l-gede-kesuk-lagi-viral-bokep-dood-tele"},{"download_url":"https://playmogo.com/d/oe3lu0echagj","si":"https://thumbcdn.com/snaps/q0547h048mqpmxsq.jpg","f":"oe3lu0echagj","ln":183,"vw":"1278","vw_fmt":"1.3K","up":"2023-11-24 15:14:54","up_fmt":"24 Nov 2023","kt":"Video Onlyfans","as":"doodstream","up_short":"24 Nov","t":"Kumpulan Video Pap Onlyfans Nami Toket Gede Bugil Ebot Streaming Bokepsatset Pekoblive","t_esc":"Kumpulan Video Pap Onlyfans Nami Toket Gede Bugil Ebot Streaming Bokepsatset Pekoblive","seo_url":"kumpulan-video-pap-onlyfans-nami-toket-gede-bugil-ebot-streaming-bokepsatset-pekoblive"},{"download_url":"https://playmogo.com/d/8l471idszipk","si":"https://thumbcdn.com/snaps/rt4osjex60pjyxjb.jpg","f":"8l471idszipk","ln":68,"vw":"1126","vw_fmt":"1.1K","up":"2023-11-24 15:14:53","up_fmt":"24 Nov 2023","kt":"Video Bokep","as":"doodstream","up_short":"24 Nov","t":"Bokep Sewa Mahasiswi Toket Gede Di Hotel Mackyykk Bokepsin Video Sotwe Tiktok Staklam","t_esc":"Bokep Sewa Mahasiswi Toket Gede Di Hotel Mackyykk Bokepsin Video Sotwe Tiktok Staklam","seo_url":"bokep-sewa-mahasiswi-toket-gede-hotel-mackyykk-bokepsin-video-sotwe-tiktok-staklam"},{"download_url":"https://playmogo.com/d/wohlucck6xna","si":"https://thumbcdn.com/snaps/7yl9y16pnurv5rn1.jpg","f":"wohlucck6xna","ln":150,"vw":"931","vw_fmt":"931","up":"2023-11-24 15:14:51","up_fmt":"24 Nov 2023","kt":"Video Pap","as":"doodstream","up_short":"24 Nov","t":"Dapat Pap Nenen Gede Dari Ayang Doodsflix Link Pemersatu Full Album","t_esc":"Dapat Pap Nenen Gede Dari Ayang Doodsflix Link Pemersatu Full Album","seo_url":"pap-nenen-gede-ayang-doodsflix-link-pemersatu-full-album"},{"download_url":"https://playmogo.com/d/6l2jl1tzd0bl","si":"https://thumbcdn.com/snaps/3b3qn2mfoaf7n55e.jpg","f":"6l2jl1tzd0bl","ln":137,"vw":"358","vw_fmt":"358","up":"2023-11-24 15:14:50","up_fmt":"24 Nov 2023","kt":"Video Gadis","as":"doodstream","up_short":"24 Nov","t":"Gadis Mulus Tatoan Toket Gede Dood Tele Pekoblive Bokepind","t_esc":"Gadis Mulus Tatoan Toket Gede Dood Tele Pekoblive Bokepind","seo_url":"gadis-mulus-tatoan-toket-gede-dood-tele-pekoblive-bokepind"},{"download_url":"https://playmogo.com/d/au1rkxflm5uz","si":"https://thumbcdn.com/snaps/wmlqbyr5jf0rjw31.jpg","f":"au1rkxflm5uz","ln":166,"vw":"811","vw_fmt":"811","up":"2023-11-24 15:14:50","up_fmt":"24 Nov 2023","kt":"Video Terabox","as":"doodstream","up_short":"24 Nov","t":"Gadis Mulus Tatoan Toket Gede Terabox Dood Viral Streaming","t_esc":"Gadis Mulus Tatoan Toket Gede Terabox Dood Viral Streaming","seo_url":"gadis-mulus-tatoan-toket-gede-terabox-dood-viral-streaming"},{"download_url":"https://playmogo.com/d/kivwyh3r2969","si":"https://thumbcdn.com/snaps/g7fhd7azy1qkp8hi.jpg","f":"kivwyh3r2969","ln":274,"vw":"2760","vw_fmt":"2.8K","up":"2023-11-24 15:14:48","up_fmt":"24 Nov 2023","kt":"Video Kenyot","as":"doodstream","up_short":"24 Nov","t":"Kenyot Toket Gede Audy Pake Costum Cosplayer Maid Cafe Bokep Indo H","t_esc":"Kenyot Toket Gede Audy Pake Costum Cosplayer Maid Cafe Bokep Indo H","seo_url":"kenyot-toket-gede-audy-pake-costum-cosplayer-maid-cafe-bokep-indo-h"},{"download_url":"https://playmogo.com/d/z3bxveawpqqo","si":"https://thumbcdn.com/snaps/hz25w9tn7wzbg16g.jpg","f":"z3bxveawpqqo","ln":160,"vw":"3183","vw_fmt":"3.2K","up":"2023-11-24 15:14:47","up_fmt":"24 Nov 2023","kt":"Video Ukhti","as":"doodstream","up_short":"24 Nov","t":"Ukhti Nisa Merlin Otong Abangnya Gede Banget Smpe Bunyi Kentut Dood Stream","t_esc":"Ukhti Nisa Merlin Otong Abangnya Gede Banget Smpe Bunyi Kentut Dood Stream","seo_url":"ukhti-nisa-merlin-otong-abangnya-gede-banget-smpe-bunyi-kentut-dood-stream"},{"download_url":"https://playmogo.com/d/6dwc55bnlci4","si":"https://thumbcdn.com/snaps/mav7kuyowkfh6oe5.jpg","f":"6dwc55bnlci4","ln":175,"vw":"1874","vw_fmt":"1.9K","up":"2023-11-24 15:14:45","up_fmt":"24 Nov 2023","kt":"Video Lulustream","as":"doodstream","up_short":"24 Nov","t":"Dimasukin Batang Gede Dood Stream Lulustream Doodstreem Update","t_esc":"Dimasukin Batang Gede Dood Stream Lulustream Doodstreem Update","seo_url":"dimasukin-batang-gede-dood-stream-lulustream-doodstreem-update"},{"download_url":"https://playmogo.com/d/dfe55l5hthkq","si":"https://thumbcdn.com/snaps/0pmusacleoj8yq9r.jpg","f":"dfe55l5hthkq","ln":373,"vw":"5052","vw_fmt":"5.1K","up":"2023-11-23 20:22:09","up_fmt":"23 Nov 2023","kt":"Video Skandal","as":"doodstream","up_short":"23 Nov","t":"Skandal Video Mesum Ngentot Nungging Bokepin Bokep Dood Memeksiana","t_esc":"Skandal Video Mesum Ngentot Nungging Bokepin Bokep Dood Memeksiana","seo_url":"skandal-video-mesum-ngentot-nungging-bokepin-bokep-dood-memeksiana"},{"download_url":"https://playmogo.com/d/0drubxdzjf5a","si":"https://thumbcdn.com/snaps/y28rje4z7g1v4zld.jpg","f":"0drubxdzjf5a","ln":326,"vw":"3097","vw_fmt":"3.1K","up":"2023-11-23 20:21:57","up_fmt":"23 Nov 2023","kt":"Video Ngentot","as":"doodstream","up_short":"23 Nov","t":"Ngentot Sama Bos Di Kantor Dood Viral Pekoblive Bokep","t_esc":"Ngentot Sama Bos Di Kantor Dood Viral Pekoblive Bokep","seo_url":"ngentot-sama-bos-kantor-dood-viral-pekoblive-bokep"},{"download_url":"https://playmogo.com/d/aw1ubd7wfy7q","si":"https://thumbcdn.com/snaps/egog969n1unc9be6.jpg","f":"aw1ubd7wfy7q","ln":101,"vw":"1411","vw_fmt":"1.4K","up":"2023-11-23 20:21:53","up_fmt":"23 Nov 2023","kt":"Video Abg","as":"doodstream","up_short":"23 Nov","t":"Abg Hijabers Jago Banget Nyepongnya Dood Stream Bokepind Video Wiki Bokep","t_esc":"Abg Hijabers Jago Banget Nyepongnya Dood Stream Bokepind Video Wiki Bokep","seo_url":"abg-hijabers-jago-banget-nyepongnya-dood-stream-bokepind-video-wiki-bokep"},{"download_url":"https://playmogo.com/d/5ikbb1a6iq55","si":"https://thumbcdn.com/snaps/mpr0jmbadpkdihd7.jpg","f":"5ikbb1a6iq55","ln":175,"vw":"636","vw_fmt":"636","up":"2023-11-23 20:21:52","up_fmt":"23 Nov 2023","kt":"Video Skandal","as":"doodstream","up_short":"23 Nov","t":"Tante Nusantara Pamer Toket Full Album Skandal Mesum Xpanas","t_esc":"Tante Nusantara Pamer Toket Full Album Skandal Mesum Xpanas","seo_url":"tante-nusantara-pamer-toket-full-album-skandal-mesum-xpanas"},{"download_url":"https://playmogo.com/d/vgfkhtbe05sy","si":"https://thumbcdn.com/snaps/6oemcsysp52w4k5d.jpg","f":"vgfkhtbe05sy","ln":171,"vw":"1243","vw_fmt":"1.2K","up":"2023-11-23 20:21:40","up_fmt":"23 Nov 2023","kt":"Video Sma","as":"doodstream","up_short":"23 Nov","t":"Sma Hijabers Montok Banget Colmek Pake Dildo Lagi Viral Website Popstream","t_esc":"Sma Hijabers Montok Banget Colmek Pake Dildo Lagi Viral Website Popstream","seo_url":"sma-hijabers-montok-banget-colmek-pake-dildo-lagi-viral-website-popstream"},{"download_url":"https://playmogo.com/d/ns8vh7by9i5m","si":"https://thumbcdn.com/snaps/t9eg3sjypmbcn53t.jpg","f":"ns8vh7by9i5m","ln":292,"vw":"1161","vw_fmt":"1.2K","up":"2023-11-23 20:21:38","up_fmt":"23 Nov 2023","kt":"Video Abg","as":"doodstream","up_short":"23 Nov","t":"Abg Hijabers Toket Bulet Banget Ebot Guling Pejuang Lendir Video Yandex Yakwad","t_esc":"Abg Hijabers Toket Bulet Banget Ebot Guling Pejuang Lendir Video Yandex Yakwad","seo_url":"abg-hijabers-toket-bulet-banget-ebot-guling-pejuang-lendir-video-yandex-yakwad"},{"download_url":"https://playmogo.com/d/rcmreeldbt9u","si":"https://thumbcdn.com/snaps/ow4zob0904q1gcv0.jpg","f":"rcmreeldbt9u","ln":89,"vw":"1899","vw_fmt":"1.9K","up":"2023-11-23 20:21:38","up_fmt":"23 Nov 2023","kt":"Video Abg","as":"doodstream","up_short":"23 Nov","t":"Abg Hijabers Toketnya Gede Banget Doodsflix Bokep Pejuang Lendir","t_esc":"Abg Hijabers Toketnya Gede Banget Doodsflix Bokep Pejuang Lendir","seo_url":"abg-hijabers-toketnya-gede-banget-doodsflix-bokep-pejuang-lendir"},{"download_url":"https://playmogo.com/d/h5j3ago3g31t","si":"https://thumbcdn.com/snaps/amvzyq4ofzhhilnl.jpg","f":"h5j3ago3g31t","ln":376,"vw":"1839","vw_fmt":"1.8K","up":"2023-11-23 20:21:36","up_fmt":"23 Nov 2023","kt":"Video Doodstream","as":"doodstream","up_short":"23 Nov","t":"Abg Hijabers Montok Colmek Telegram Bokep Doodstream","t_esc":"Abg Hijabers Montok Colmek Telegram Bokep Doodstream","seo_url":"abg-hijabers-montok-colmek-telegram-bokep-doodstream"},{"download_url":"https://playmogo.com/d/6q8pfj75qm33","si":"https://thumbcdn.com/snaps/w2exvrajd4b3jkk0.jpg","f":"6q8pfj75qm33","ln":537,"vw":"1870","vw_fmt":"1.9K","up":"2023-11-23 20:21:36","up_fmt":"23 Nov 2023","kt":"Video Vcs","as":"doodstream","up_short":"23 Nov","t":"Hijabers Toge Buljem Lebat Vcs Omek Bokep Video Yandex Indo","t_esc":"Hijabers Toge Buljem Lebat Vcs Omek Bokep Video Yandex Indo","seo_url":"hijabers-toge-buljem-lebat-vcs-omek-bokep-video-yandex-indo"}],"results_total":"26447","results":30}}