{"msg":"OK","server_time":"2026-04-04 04:55:41","status":200,"result":{"total_pages":882,"files":[{"download_url":"https://playmogo.com/d/1via2mmdd0cs","si":"https://thumbcdn.com/snaps/0o19i4pmal7at47y.jpg","f":"1via2mmdd0cs","ln":59,"vw":"12254","vw_fmt":"12.3K","up":"2023-08-05 21:00:18","up_fmt":"5 Agu 2023","kt":"Video Bokep","as":"doodstream","up_short":"5 Agu","t":"Bokep Viral Artis Indo Gemoy Bokepin Links Tele Terupdate","t_esc":"Bokep Viral Artis Indo Gemoy Bokepin Links Tele Terupdate","seo_url":"bokep-viral-artis-indo-gemoy-bokepin-links-tele-terupdate"},{"download_url":"https://playmogo.com/d/iyg3glczvwxf","si":"https://thumbcdn.com/snaps/1ql791nhgw6u0lyc.jpg","f":"iyg3glczvwxf","ln":211,"vw":"4079","vw_fmt":"4.1K","up":"2023-08-05 21:00:17","up_fmt":"5 Agu 2023","kt":"Video Skandal","as":"doodstream","up_short":"5 Agu","t":"Bokep Viral Indo Terbaru Gemoy Bokepsatset Skandal Mesum Staklam","t_esc":"Bokep Viral Indo Terbaru Gemoy Bokepsatset Skandal Mesum Staklam","seo_url":"bokep-viral-indo-terbaru-gemoy-bokepsatset-skandal-mesum-staklam"},{"download_url":"https://playmogo.com/d/ryrzldhlvs66","si":"https://thumbcdn.com/snaps/pyco44mybhm0nyms.jpg","f":"ryrzldhlvs66","ln":935,"vw":"1763","vw_fmt":"1.8K","up":"2023-08-05 21:00:13","up_fmt":"5 Agu 2023","kt":"Video Bokep","as":"doodstream","up_short":"5 Agu","t":"Bokep Tante Vs Ponakan Gemoy Staklam Videos Video Yandex","t_esc":"Bokep Tante Vs Ponakan Gemoy Staklam Videos Video Yandex","seo_url":"bokep-tante-vs-ponakan-gemoy-staklam-videos-video-yandex"},{"download_url":"https://playmogo.com/d/zj9wc0g4omwu","si":"https://thumbcdn.com/snaps/nkp2r90eeaar38l1.jpg","f":"zj9wc0g4omwu","ln":305,"vw":"4198","vw_fmt":"4.2K","up":"2023-08-05 21:00:12","up_fmt":"5 Agu 2023","kt":"Video Bokep","as":"doodstream","up_short":"5 Agu","t":"Bokep Wanita Hamil Tua Gemoy Dood Links Tele Video Wiki","t_esc":"Bokep Wanita Hamil Tua Gemoy Dood Links Tele Video Wiki","seo_url":"bokep-wanita-hamil-tua-gemoy-dood-links-tele-video-wiki"},{"download_url":"https://playmogo.com/d/ksszpjks3kum","si":"https://thumbcdn.com/snaps/2k6roktaty26pog8.jpg","f":"ksszpjks3kum","ln":294,"vw":"1435","vw_fmt":"1.4K","up":"2023-08-05 21:00:11","up_fmt":"5 Agu 2023","kt":"Video Telegram","as":"doodstream","up_short":"5 Agu","t":"Cari Video Bokep Indonesia Gemoy Pekoblive Videy Link Telegram Wiki","t_esc":"Cari Video Bokep Indonesia Gemoy Pekoblive Videy Link Telegram Wiki","seo_url":"cari-video-bokep-indonesia-gemoy-pekoblive-videy-link-telegram-wiki"},{"download_url":"https://playmogo.com/d/rma3wqam0app","si":"https://thumbcdn.com/snaps/0iefqrwr5th7da39.jpg","f":"rma3wqam0app","ln":437,"vw":"5145","vw_fmt":"5.1K","up":"2023-08-05 21:00:10","up_fmt":"5 Agu 2023","kt":"Video Cara","as":"doodstream","up_short":"5 Agu","t":"Cara Nonton Bokep Anime Gemoy Terupdate Bokepsin Update","t_esc":"Cara Nonton Bokep Anime Gemoy Terupdate Bokepsin Update","seo_url":"cara-nonton-bokep-anime-gemoy-terupdate-bokepsin-update"},{"download_url":"https://playmogo.com/d/25ky0zkkg0lt","si":"https://thumbcdn.com/snaps/vyf68t50vio6hv7y.jpg","f":"25ky0zkkg0lt","ln":736,"vw":"7905","vw_fmt":"7.9K","up":"2023-08-05 21:00:05","up_fmt":"5 Agu 2023","kt":"Video Jav","as":"doodstream","up_short":"5 Agu","t":"Download Bokep Jav Hd Gemoy Bokepin Video Yandex Sotwe","t_esc":"Download Bokep Jav Hd Gemoy Bokepin Video Yandex Sotwe","seo_url":"download-bokep-jav-hd-gemoy-bokepin-video-yandex-sotwe"},{"download_url":"https://playmogo.com/d/nk84kczdslws","si":"https://thumbcdn.com/snaps/6z8w4n1klh2uubnw.jpg","f":"nk84kczdslws","ln":1137,"vw":"10371","vw_fmt":"10.4K","up":"2023-08-05 20:59:24","up_fmt":"5 Agu 2023","kt":"Video Jepang","as":"doodstream","up_short":"5 Agu","t":"Download Bokep Jepang Kakek Gemoy Bokepin Pekoblive Twitter","t_esc":"Download Bokep Jepang Kakek Gemoy Bokepin Pekoblive Twitter","seo_url":"download-bokep-jepang-kakek-gemoy-bokepin-pekoblive-twitter"},{"download_url":"https://playmogo.com/d/0y6r9d0jz1sh","si":"https://thumbcdn.com/snaps/ky7fmck6aqcpa3uk.jpg","f":"0y6r9d0jz1sh","ln":478,"vw":"3740","vw_fmt":"3.7K","up":"2023-08-05 20:59:23","up_fmt":"5 Agu 2023","kt":"Video Jepang","as":"doodstream","up_short":"5 Agu","t":"Download Bokep Jepang Mp Gemoy Asupan Viral Streaming Doods Pro","t_esc":"Download Bokep Jepang Mp Gemoy Asupan Viral Streaming Doods Pro","seo_url":"download-bokep-jepang-mp-gemoy-asupan-viral-streaming-doods-pro"},{"download_url":"https://playmogo.com/d/myj3a8y73f9a","si":"https://thumbcdn.com/snaps/bov82cb8k50s49pm.jpg","f":"myj3a8y73f9a","ln":887,"vw":"22415","vw_fmt":"22.4K","up":"2023-08-05 20:59:23","up_fmt":"5 Agu 2023","kt":"Video Jepang","as":"doodstream","up_short":"5 Agu","t":"Download Bokep Jepang Perkosa Gemoy Pejuang Lendir Doodstreem Dodstream","t_esc":"Download Bokep Jepang Perkosa Gemoy Pejuang Lendir Doodstreem Dodstream","seo_url":"download-bokep-jepang-perkosa-gemoy-pejuang-lendir-doodstreem-dodstream"},{"download_url":"https://playmogo.com/d/xc9nm6ypoka8","si":"https://thumbcdn.com/snaps/38541bzwlfmm0ese.jpg","f":"xc9nm6ypoka8","ln":736,"vw":"13010","vw_fmt":"13.0K","up":"2023-08-05 20:59:22","up_fmt":"5 Agu 2023","kt":"Video Jepang","as":"doodstream","up_short":"5 Agu","t":"Ngentot Jepang Montok Perkosa Memeksiana Dood Tele Bokepsin","t_esc":"Ngentot Jepang Montok Perkosa Memeksiana Dood Tele Bokepsin","seo_url":"ngentot-jepang-montok-perkosa-memeksiana-dood-tele-bokepsin"},{"download_url":"https://playmogo.com/d/4egvehofmqjv","si":"https://thumbcdn.com/snaps/v3rjhf9fxbcsbiyh.jpg","f":"4egvehofmqjv","ln":188,"vw":"430","vw_fmt":"430","up":"2023-08-05 20:59:22","up_fmt":"5 Agu 2023","kt":"Video Bebasindo","as":"doodstream","up_short":"5 Agu","t":"Download Bokep Psk Indo Gemoy Yakwad Toketbagus Bebasindo","t_esc":"Download Bokep Psk Indo Gemoy Yakwad Toketbagus Bebasindo","seo_url":"download-bokep-psk-indo-gemoy-yakwad-toketbagus-bebasindo"},{"download_url":"https://playmogo.com/d/3kj5jo2gq0nq","si":"https://thumbcdn.com/snaps/fbn3uv8ofdjxtyko.jpg","f":"3kj5jo2gq0nq","ln":481,"vw":"904","vw_fmt":"904","up":"2023-08-05 20:59:14","up_fmt":"5 Agu 2023","kt":"Video Telegram","as":"doodstream","up_short":"5 Agu","t":"Download Bokep Smu Indo Gemoy Memeksiana Videy Link Telegram Lagi Viral","t_esc":"Download Bokep Smu Indo Gemoy Memeksiana Videy Link Telegram Lagi Viral","seo_url":"download-bokep-smu-indo-gemoy-memeksiana-videy-link-telegram-lagi-viral"},{"download_url":"https://playmogo.com/d/2id5uxcac0tb","si":"https://thumbcdn.com/snaps/d05bn677llhdzl8s.jpg","f":"2id5uxcac0tb","ln":1224,"vw":"8508","vw_fmt":"8.5K","up":"2023-08-05 20:59:13","up_fmt":"5 Agu 2023","kt":"Video Bebasindo","as":"doodstream","up_short":"5 Agu","t":"Download Bokep Pijat Sex Gemoy Video Memeksiana Bebasindo","t_esc":"Download Bokep Pijat Sex Gemoy Video Memeksiana Bebasindo","seo_url":"download-bokep-pijat-sex-gemoy-video-memeksiana-bebasindo"},{"download_url":"https://playmogo.com/d/3a16ydkiux21","si":"https://thumbcdn.com/snaps/rgzy7pmabgo68pkz.jpg","f":"3a16ydkiux21","ln":1575,"vw":"5349","vw_fmt":"5.3K","up":"2023-08-05 20:59:12","up_fmt":"5 Agu 2023","kt":"Video Memeksiana","as":"doodstream","up_short":"5 Agu","t":"Download Bokep Selingkuh Full Durasi Gemoy Memeksiana Bokepin Doodsflix","t_esc":"Download Bokep Selingkuh Full Durasi Gemoy Memeksiana Bokepin Doodsflix","seo_url":"download-bokep-selingkuh-full-durasi-gemoy-memeksiana-bokepin-doodsflix"},{"download_url":"https://playmogo.com/d/dw3v44jo5cpi","si":"https://thumbcdn.com/snaps/f9u5be2f5gawqmxr.jpg","f":"dw3v44jo5cpi","ln":301,"vw":"7210","vw_fmt":"7.2K","up":"2023-08-05 20:59:11","up_fmt":"5 Agu 2023","kt":"Video Jepang","as":"doodstream","up_short":"5 Agu","t":"Download Film Bokep Jepang Gemoy Doodflix Bokepin Doodstreem","t_esc":"Download Film Bokep Jepang Gemoy Doodflix Bokepin Doodstreem","seo_url":"download-film-bokep-jepang-gemoy-doodflix-bokepin-doodstreem"},{"download_url":"https://playmogo.com/d/pwqprzl36cdb","si":"https://thumbcdn.com/snaps/p4od3z33stjw2ga8.jpg","f":"pwqprzl36cdb","ln":736,"vw":"6577","vw_fmt":"6.6K","up":"2023-08-05 20:59:10","up_fmt":"5 Agu 2023","kt":"Video Jepang","as":"doodstream","up_short":"5 Agu","t":"Ngentot Jepang Montok Film Bokep Free Streaming Video Doodstreem","t_esc":"Ngentot Jepang Montok Film Bokep Free Streaming Video Doodstreem","seo_url":"ngentot-jepang-montok-film-bokep-free-streaming-video-doodstreem"},{"download_url":"https://playmogo.com/d/qc9t740cp35h","si":"https://thumbcdn.com/snaps/znzq4vyvauajz155.jpg","f":"qc9t740cp35h","ln":561,"vw":"945","vw_fmt":"945","up":"2023-08-05 20:59:10","up_fmt":"5 Agu 2023","kt":"Video Download","as":"doodstream","up_short":"5 Agu","t":"Download Film Bokep Korea Gemoy Doodflix Full Album Bokepsin","t_esc":"Download Film Bokep Korea Gemoy Doodflix Full Album Bokepsin","seo_url":"download-film-bokep-korea-gemoy-doodflix-full-album-bokepsin"},{"download_url":"https://playmogo.com/d/x6r3zn8aet3d","si":"https://thumbcdn.com/snaps/7qzi7zcn8716bvhi.jpg","f":"x6r3zn8aet3d","ln":69,"vw":"2058","vw_fmt":"2.1K","up":"2023-08-05 20:59:09","up_fmt":"5 Agu 2023","kt":"Video Simontok","as":"doodstream","up_short":"5 Agu","t":"Download Film Bokep Sub Indo Gemoy Xpanas Asupan Viral Simontok","t_esc":"Download Film Bokep Sub Indo Gemoy Xpanas Asupan Viral Simontok","seo_url":"download-film-bokep-sub-indo-gemoy-xpanas-asupan-viral-simontok"},{"download_url":"https://playmogo.com/d/emcbkask05rc","si":"https://thumbcdn.com/snaps/twgn077wiapxnb5e.jpg","f":"emcbkask05rc","ln":180,"vw":"3838","vw_fmt":"3.8K","up":"2023-08-05 20:59:09","up_fmt":"5 Agu 2023","kt":"Video Lulustream","as":"doodstream","up_short":"5 Agu","t":"Download Film Semi Bokep Sub Indo Gemoy Video Asupan Viral Lulustream","t_esc":"Download Film Semi Bokep Sub Indo Gemoy Video Asupan Viral Lulustream","seo_url":"download-film-semi-bokep-sub-indo-gemoy-video-asupan-viral-lulustream"},{"download_url":"https://playmogo.com/d/8efqc6tk0xgg","si":"https://thumbcdn.com/snaps/11x2wmmmhg4psptf.jpg","f":"8efqc6tk0xgg","ln":651,"vw":"1969","vw_fmt":"2.0K","up":"2023-08-05 20:59:07","up_fmt":"5 Agu 2023","kt":"Video Jepang","as":"doodstream","up_short":"5 Agu","t":"Download Situs Bokep Jepang Gemoy Full Album Doods Pro Doodstreem","t_esc":"Download Situs Bokep Jepang Gemoy Full Album Doods Pro Doodstreem","seo_url":"download-situs-bokep-jepang-gemoy-full-album-doods-pro-doodstreem"},{"download_url":"https://playmogo.com/d/hy6lle53jtou","si":"https://thumbcdn.com/snaps/cwh9vadp43e72odu.jpg","f":"hy6lle53jtou","ln":388,"vw":"18015","vw_fmt":"18.0K","up":"2023-08-05 20:59:06","up_fmt":"5 Agu 2023","kt":"Video Skandal","as":"doodstream","up_short":"5 Agu","t":"Download Video Bokep Anime Naruto Gemoy Bebasindo Toketbagus Skandal Mesum","t_esc":"Download Video Bokep Anime Naruto Gemoy Bebasindo Toketbagus Skandal Mesum","seo_url":"download-video-bokep-anime-naruto-gemoy-bebasindo-toketbagus-skandal-mesum"},{"download_url":"https://playmogo.com/d/kxsq5g4egswf","si":"https://thumbcdn.com/snaps/44pyeq3dzjqbsmy2.jpg","f":"kxsq5g4egswf","ln":352,"vw":"9275","vw_fmt":"9.3K","up":"2023-08-05 20:59:05","up_fmt":"5 Agu 2023","kt":"Video Jepang","as":"doodstream","up_short":"5 Agu","t":"Download Video Bokep Anime Jepang Gemoy Pekoblive Yandex Link Asupan","t_esc":"Download Video Bokep Anime Jepang Gemoy Pekoblive Yandex Link Asupan","seo_url":"download-video-bokep-anime-jepang-gemoy-pekoblive-yandex-link-asupan"},{"download_url":"https://playmogo.com/d/f5f02etoqzu0","si":"https://thumbcdn.com/snaps/bhzzroa7b8haglgq.jpg","f":"f5f02etoqzu0","ln":389,"vw":"25560","vw_fmt":"25.6K","up":"2023-08-05 20:59:04","up_fmt":"5 Agu 2023","kt":"Video Download","as":"doodstream","up_short":"5 Agu","t":"Download Video Bokep Arab Gemoy Link Asupan Sotwe Wiki","t_esc":"Download Video Bokep Arab Gemoy Link Asupan Sotwe Wiki","seo_url":"download-video-bokep-arab-gemoy-link-asupan-sotwe-wiki"},{"download_url":"https://playmogo.com/d/u1y98evt99kt","si":"https://thumbcdn.com/snaps/c2nszq5eqrlvx8nc.jpg","f":"u1y98evt99kt","ln":806,"vw":"1058","vw_fmt":"1.1K","up":"2023-08-05 20:59:03","up_fmt":"5 Agu 2023","kt":"Video Download","as":"doodstream","up_short":"5 Agu","t":"Download Video Bokep Asian Sex Diary Gemoy Asupan Viral Lagi Yandex","t_esc":"Download Video Bokep Asian Sex Diary Gemoy Asupan Viral Lagi Yandex","seo_url":"download-video-bokep-asian-sex-diary-gemoy-asupan-viral-lagi-yandex"},{"download_url":"https://playmogo.com/d/aia94rd53ho8","si":"https://thumbcdn.com/snaps/j7j93rmeh2vuw4jl.jpg","f":"aia94rd53ho8","ln":967,"vw":"3107","vw_fmt":"3.1K","up":"2023-08-05 20:59:02","up_fmt":"5 Agu 2023","kt":"Video Download","as":"doodstream","up_short":"5 Agu","t":"Download Video Bokep Japan Gemoy Yakwad Poophd","t_esc":"Download Video Bokep Japan Gemoy Yakwad Poophd","seo_url":"download-video-bokep-japan-gemoy-yakwad-poophd"},{"download_url":"https://playmogo.com/d/k8f8cjg4uxxd","si":"https://thumbcdn.com/snaps/8hdfbqvfpztq64tt.jpg","f":"k8f8cjg4uxxd","ln":732,"vw":"7300","vw_fmt":"7.3K","up":"2023-08-05 20:59:02","up_fmt":"5 Agu 2023","kt":"Video Jepang","as":"doodstream","up_short":"5 Agu","t":"Download Video Bokep Jepang Durasi Panjang Gemoy Memeksiana Doodflix Terupdate","t_esc":"Download Video Bokep Jepang Durasi Panjang Gemoy Memeksiana Doodflix Terupdate","seo_url":"download-video-bokep-jepang-durasi-panjang-gemoy-memeksiana-doodflix-terupdate"},{"download_url":"https://playmogo.com/d/l8i5iucfoct0","si":"https://thumbcdn.com/snaps/54wyr1bjbo0c7qiz.jpg","f":"l8i5iucfoct0","ln":310,"vw":"2692","vw_fmt":"2.7K","up":"2023-08-05 20:58:57","up_fmt":"5 Agu 2023","kt":"Video Hot","as":"doodstream","up_short":"5 Agu","t":"Download Video Bokep Jepang Hot Gemoy Staklam Asupan Viral Dood","t_esc":"Download Video Bokep Jepang Hot Gemoy Staklam Asupan Viral Dood","seo_url":"download-video-bokep-jepang-hot-gemoy-staklam-asupan-viral-dood"},{"download_url":"https://playmogo.com/d/my07ywsdrrzg","si":"https://thumbcdn.com/snaps/abv6fpjezrwxtekl.jpg","f":"my07ywsdrrzg","ln":4370,"vw":"8727","vw_fmt":"8.7K","up":"2023-08-05 20:58:55","up_fmt":"5 Agu 2023","kt":"Video Terabox","as":"doodstream","up_short":"5 Agu","t":"Download Video Bokep Korea Gemoy Terabox Yakwad Sotwe","t_esc":"Download Video Bokep Korea Gemoy Terabox Yakwad Sotwe","seo_url":"download-video-bokep-korea-gemoy-terabox-yakwad-sotwe"},{"download_url":"https://playmogo.com/d/t8dehk39hgj0","si":"https://thumbcdn.com/snaps/1vp9xpfumiuelihn.jpg","f":"t8dehk39hgj0","ln":313,"vw":"8350","vw_fmt":"8.3K","up":"2023-08-05 20:58:54","up_fmt":"5 Agu 2023","kt":"Video Telegram","as":"doodstream","up_short":"5 Agu","t":"Download Video Bokep Mom And Son Jepang Gemoy Full Album Link Asupan Videy Telegram","t_esc":"Download Video Bokep Mom And Son Jepang Gemoy Full Album Link Asupan Videy Telegram","seo_url":"download-video-bokep-mom-and-son-jepang-gemoy-full-album-link-asupan-videy-telegram"}],"results_total":"26452","results":30}}